{
  "totalGoodbom": "861.15",
  "totalTenda": "1599.10",
  "totalArena": "1629.58",
  "totalSavegnago": "863.72",
  "produtos": [
    {
      "id": "2",
      "goodbom": {
        "nome": "BACON PEDAÇO",
        "preco": 0,
        "preco_por_kg": 0
      },
      "tenda": {
        "nome": "Bacon Pedaço Sadia 500g",
        "preco": 14.75,
        "preco_por_kg": 29.5
      },
      "arena": {
        "nome": null,
        "preco": 0,
        "preco_por_kg": 0
      },
      "savegnago": {
        "nome": "BACON PEDAÇO",
        "preco": 0,
        "preco_por_kg": 0
      },
      "mais_barato": "Tenda"
    },
    {
      "id": "3",
      "goodbom": {
        "nome": "LINGUIÇA CALABRESA CERATTI FATIADO 100G",
        "preco": 11.99,
        "preco_por_kg": 119.9
      },
      "tenda": {
        "nome": "Linguiça Calabresa Brasa 400g",
        "preco": 13.39,
        "preco_por_kg": 33.48
      },
      "arena": {
        "nome": "Linguiça Tipo Calabresa Defumada 400g",
        "preco": 11.49,
        "preco_por_kg": 28.72
      },
      "savegnago": {
        "nome": "Linguiça Calabresa Cozida Defumada Sadia 400g",
        "preco": 14.9,
        "preco_por_kg": 37.25
      },
      "mais_barato": "Arena"
    },
    {
      "id": "5",
      "goodbom": {
        "nome": "LINGUIÇA TOSCANA AURORA KG",
        "preco": 18.99,
        "preco_por_kg": 18.99
      },
      "tenda": {
        "nome": "Linguiça Toscana Congelada Pérola 500g",
        "preco": 7.95,
        "preco_por_kg": 15.9
      },
      "arena": {
        "nome": "Linguiça Toscana Frimesa Bandeja Kg",
        "preco": 22.9,
        "preco_por_kg": 22.9
      },
      "savegnago": {
        "nome": "Linguiça Toscana Churrasco Seara 700g",
        "preco": 24.9,
        "preco_por_kg": 35.57
      },
      "mais_barato": "Tenda"
    },
    {
      "id": "6",
      "goodbom": {
        "nome": "SALSICHA HOT DOG SEARA KG",
        "preco": 9.99,
        "preco_por_kg": 9.99
      },
      "tenda": {
        "nome": "Salsicha Hot Dog Aurora Pacote 3kg",
        "preco": 26.97,
        "preco_por_kg": 8.99
      },
      "arena": {
        "nome": "Salsicha Hot Dog Copacol Granel Kg",
        "preco": 8.99,
        "preco_por_kg": 8.99
      },
      "savegnago": {
        "nome": "Salsicha Hot Dog Perdigão 500g",
        "preco": 11.9,
        "preco_por_kg": 23.8
      },
      "mais_barato": "Tenda"
    },
    {
      "id": "7",
      "goodbom": {
        "nome": "SOBRECOXA DE FRANGO SWIFT 1KG",
        "preco": 14.5,
        "preco_por_kg": 14.5
      },
      "tenda": {
        "nome": "Sobrecoxa Seara IQF 1kg",
        "preco": 12.9,
        "preco_por_kg": 12.9
      },
      "arena": {
        "nome": "Sobrecoxa Bandeja Kg",
        "preco": 14.9,
        "preco_por_kg": 14.9
      },
      "savegnago": {
        "nome": "Sobrecoxa Seara 1kg",
        "preco": 17.9,
        "preco_por_kg": 17.9
      },
      "mais_barato": "Tenda"
    },
    {
      "id": "10",
      "goodbom": {
        "nome": "MIOLO DA ALCATRA",
        "preco": 0,
        "preco_por_kg": 0
      },
      "tenda": {
        "nome": "Miolo da Alcatra Bovina Resfriado em Bifes bandeja 400g",
        "preco": 18.76,
        "preco_por_kg": 46.9
      },
      "arena": {
        "nome": "Miolo Alcatra Bovino Porcionado Kg",
        "preco": 48.9,
        "preco_por_kg": 48.9
      },
      "savegnago": {
        "nome": "MIOLO DA ALCATRA",
        "preco": 0,
        "preco_por_kg": 0
      },
      "mais_barato": "Tenda"
    },
    {
      "id": "11",
      "goodbom": {
        "nome": "CONTRA FILÉ BOVINO",
        "preco": 0,
        "preco_por_kg": 0
      },
      "tenda": {
        "nome": "Contra Filé Bovino em Bifes Resfriado Bandeja 400g",
        "preco": 21.16,
        "preco_por_kg": 52.9
      },
      "arena": {
        "nome": "Contra Filé Bovino Porcionado Embalado À Vácuo Kg",
        "preco": 46.9,
        "preco_por_kg": 46.9
      },
      "savegnago": {
        "nome": "Contra Filé Bovino Peça Vácuo 3,5kg",
        "preco": 98.9,
        "preco_por_kg": 28.26
      },
      "mais_barato": "Savegnago"
    },
    {
      "id": "12",
      "goodbom": {
        "nome": "MÚSCULO BOVINO",
        "preco": 0,
        "preco_por_kg": 0
      },
      "tenda": {
        "nome": "Músculo Bovino Resfriado Peça 4kg",
        "preco": 111.6,
        "preco_por_kg": 27.9
      },
      "arena": {
        "nome": "Músculo Bovino Bandeja Kg",
        "preco": 39.9,
        "preco_por_kg": 39.9
      },
      "savegnago": {
        "nome": "MÚSCULO BOVINO",
        "preco": 0,
        "preco_por_kg": 0
      },
      "mais_barato": "Tenda"
    },
    {
      "id": "19",
      "goodbom": {
        "nome": "PIMENTÃO VERMELHO KG",
        "preco": 31.99,
        "preco_por_kg": 31.99
      },
      "tenda": {
        "nome": "Pimentão Vermelho 350g",
        "preco": 11.89,
        "preco_por_kg": 33.97
      },
      "arena": {
        "nome": "Pimentão Vermelho Kg",
        "preco": 24.89,
        "preco_por_kg": 24.89
      },
      "savegnago": {
        "nome": "PIMENTÃO VERMELHO",
        "preco": 0,
        "preco_por_kg": 0
      },
      "mais_barato": "Arena"
    },
    {
      "id": "24",
      "goodbom": {
        "nome": "BETERRABA KG",
        "preco": 3.99,
        "preco_por_kg": 3.99
      },
      "tenda": {
        "nome": "Beterraba Saco 1Kg",
        "preco": 2.99,
        "preco_por_kg": 2.99
      },
      "arena": {
        "nome": "Beterraba Kg",
        "preco": 4.79,
        "preco_por_kg": 4.79
      },
      "savegnago": {
        "nome": "Beterraba 1Kg",
        "preco": 2.95,
        "preco_por_kg": 2.95
      },
      "mais_barato": "Savegnago"
    },
    {
      "id": "26",
      "goodbom": {
        "nome": "GENGIBRE KG",
        "preco": 11.99,
        "preco_por_kg": 11.99
      },
      "tenda": {
        "nome": "Gengibre Unidade",
        "preco": 1.48,
        "preco_por_kg": 1.48
      },
      "arena": {
        "nome": "Chá Verde Natural Tea Laranja E Gengibre 1l",
        "preco": 6.59,
        "preco_por_kg": 6.59
      },
      "savegnago": {
        "nome": "Gengibre Bandeja 350g",
        "preco": 5.25,
        "preco_por_kg": 15
      },
      "mais_barato": "Tenda"
    },
    {
      "id": "27",
      "goodbom": {
        "nome": "CENOURA KG",
        "preco": 3.99,
        "preco_por_kg": 3.99
      },
      "tenda": {
        "nome": "Cenoura Bandeja 500g",
        "preco": 2.99,
        "preco_por_kg": 5.98
      },
      "arena": {
        "nome": "Cenoura Kg",
        "preco": 3.99,
        "preco_por_kg": 3.99
      },
      "savegnago": {
        "nome": "Cenoura 1Kg",
        "preco": 2.95,
        "preco_por_kg": 2.95
      },
      "mais_barato": "Savegnago"
    },
    {
      "id": "28",
      "goodbom": {
        "nome": "CHUCHU KG",
        "preco": 8.99,
        "preco_por_kg": 8.99
      },
      "tenda": {
        "nome": "Chuchu Unidade",
        "preco": 1.85,
        "preco_por_kg": 1.85
      },
      "arena": {
        "nome": "Chuchu Kg",
        "preco": 4.29,
        "preco_por_kg": 4.29
      },
      "savegnago": {
        "nome": "Chuchu 1kg",
        "preco": 3.49,
        "preco_por_kg": 3.49
      },
      "mais_barato": "Tenda"
    },
    {
      "id": "29",
      "goodbom": {
        "nome": "MANDIOQUINHA KG",
        "preco": 9.99,
        "preco_por_kg": 9.99
      },
      "tenda": {
        "nome": "Mandioquinha Unidade",
        "preco": 2.06,
        "preco_por_kg": 2.06
      },
      "arena": {
        "nome": "Mandioquinha Kg",
        "preco": 25.9,
        "preco_por_kg": 25.9
      },
      "savegnago": {
        "nome": "Mandioquinha Vapza 500g",
        "preco": 21.9,
        "preco_por_kg": 43.8
      },
      "mais_barato": "Tenda"
    },
    {
      "id": "30",
      "goodbom": {
        "nome": "CHEIRO VERDE",
        "preco": 0,
        "preco_por_kg": 0
      },
      "tenda": {
        "nome": "Cheiro Verde Maço Unidade",
        "preco": 4.29,
        "preco_por_kg": 4.29
      },
      "arena": {
        "nome": "Cheiro Verde Jw Unid.",
        "preco": 3.79,
        "preco_por_kg": 3.79
      },
      "savegnago": {
        "nome": "Cheiro Verde La Vita PicadoPacote 60g",
        "preco": 6.29,
        "preco_por_kg": 104.83
      },
      "mais_barato": "Arena"
    },
    {
      "id": "31",
      "goodbom": {
        "nome": "ALFACE CRESPA UN",
        "preco": 2.99,
        "preco_por_kg": 2.99
      },
      "tenda": {
        "nome": "Alface Roxa Unidade",
        "preco": 4.49,
        "preco_por_kg": 4.49
      },
      "arena": {
        "nome": "Alface Crespa Hidropônica Jw Unid.",
        "preco": 4.19,
        "preco_por_kg": 4.19
      },
      "savegnago": {
        "nome": "Alface Americana Bola La Vita Bandeja 250g",
        "preco": 6.49,
        "preco_por_kg": 25.96
      },
      "mais_barato": "Goodbom"
    },
    {
      "id": "32",
      "goodbom": {
        "nome": "REPOLHO LISO KG",
        "preco": 1.99,
        "preco_por_kg": 1.99
      },
      "tenda": {
        "nome": "Repolho Verde Unidade",
        "preco": 3.79,
        "preco_por_kg": 3.79
      },
      "arena": {
        "nome": "Repolho Verde Kg",
        "preco": 4.89,
        "preco_por_kg": 4.89
      },
      "savegnago": {
        "nome": "Repolho Verde 2Kg",
        "preco": 5.55,
        "preco_por_kg": 2.77
      },
      "mais_barato": "Goodbom"
    },
    {
      "id": "33",
      "goodbom": {
        "nome": "ALHO DESCASCADO",
        "preco": 0,
        "preco_por_kg": 0
      },
      "tenda": {
        "nome": "Alho Descascado Kamar 200g",
        "preco": 9.89,
        "preco_por_kg": 49.45
      },
      "arena": {
        "nome": "Alho Descascado Hortmix 600g",
        "preco": 29.9,
        "preco_por_kg": 49.83
      },
      "savegnago": {
        "nome": "Alho descascado Natari 1Kg",
        "preco": 34.9,
        "preco_por_kg": 34.9
      },
      "mais_barato": "Savegnago"
    },
    {
      "id": "34",
      "goodbom": {
        "nome": "MAMÃO PAPAYA KG",
        "preco": 6.99,
        "preco_por_kg": 6.99
      },
      "tenda": {
        "nome": "Mamão Papaya Unidade",
        "preco": 4.79,
        "preco_por_kg": 4.79
      },
      "arena": {
        "nome": "Iogurte Desnatado Batavo Pense Zero Zero Lactose Mamão 1,150kg",
        "preco": 16.99,
        "preco_por_kg": 0.11
      },
      "savegnago": {
        "nome": "Mamão Papaya Golden 1,2Kg",
        "preco": 1.59,
        "preco_por_kg": 1.33
      },
      "mais_barato": "Arena"
    },
    {
      "id": "35",
      "goodbom": {
        "nome": "BANANA PRATA KG",
        "preco": 9.99,
        "preco_por_kg": 9.99
      },
      "tenda": {
        "nome": "Banana Prata Unidade",
        "preco": 1.5,
        "preco_por_kg": 1.5
      },
      "arena": {
        "nome": "Banana Maçã Kg",
        "preco": 11.8,
        "preco_por_kg": 11.8
      },
      "savegnago": {
        "nome": "Banana Nanica Exportação - 1kg",
        "preco": 12.55,
        "preco_por_kg": 12.55
      },
      "mais_barato": "Tenda"
    },
    {
      "id": "36",
      "goodbom": {
        "nome": "UVA NIAGARA 400G",
        "preco": 8.99,
        "preco_por_kg": 22.47
      },
      "tenda": {
        "nome": "Uva Niagara Bandeja 500g",
        "preco": 6.99,
        "preco_por_kg": 13.98
      },
      "arena": {
        "nome": "Uva Preta Sem Semente Doce Uva 500g",
        "preco": 8.79,
        "preco_por_kg": 17.58
      },
      "savegnago": {
        "nome": "UVA",
        "preco": 0,
        "preco_por_kg": 0
      },
      "mais_barato": "Tenda"
    },
    {
      "id": "37",
      "goodbom": {
        "nome": "MAÇÃ GALA KG",
        "preco": 16.99,
        "preco_por_kg": 16.99
      },
      "tenda": {
        "nome": "Maçã Nectar 850g",
        "preco": 8.29,
        "preco_por_kg": 9.75
      },
      "arena": {
        "nome": "Suco Maguary Maçã Tp 1l",
        "preco": 5.95,
        "preco_por_kg": 5.95
      },
      "savegnago": {
        "nome": "Maçã Turma Da Mônica 1kg Pacote",
        "preco": 13.9,
        "preco_por_kg": 13.9
      },
      "mais_barato": "Arena"
    },
    {
      "id": "38",
      "goodbom": {
        "nome": "MEXERICA",
        "preco": 0,
        "preco_por_kg": 0
      },
      "tenda": {
        "nome": "Mexerica Murcote 130g",
        "preco": 0.91,
        "preco_por_kg": 7
      },
      "arena": {
        "nome": "Refrigerante Bioleve Mexerica E Limão Zero Pet 1,5l",
        "preco": 5.39,
        "preco_por_kg": 1.08
      },
      "savegnago": {
        "nome": "MEXERICA",
        "preco": 0,
        "preco_por_kg": 0
      },
      "mais_barato": "Arena"
    },
    {
      "id": "39",
      "goodbom": {
        "nome": "MARGARINA DORIANA CREM.C/S 1KG",
        "preco": 17.79,
        "preco_por_kg": 17.79
      },
      "tenda": {
        "nome": "Margarina com Sal Dualis 500g",
        "preco": 3.45,
        "preco_por_kg": 6.9
      },
      "arena": {
        "nome": "Margarina Claybom Cremosa C/ 50%L C/ Sal 14kg",
        "preco": 114.9,
        "preco_por_kg": 8.21
      },
      "savegnago": {
        "nome": "Margarina Qualy 500g Com Sal",
        "preco": 7.19,
        "preco_por_kg": 14.38
      },
      "mais_barato": "Tenda"
    },
    {
      "id": "40",
      "goodbom": {
        "nome": "LEITE ZERO",
        "preco": 0,
        "preco_por_kg": 0
      },
      "tenda": {
        "nome": "Leite Zero Lactose Semidesnatado Piracanjuba 1L",
        "preco": 5.49,
        "preco_por_kg": 5.49
      },
      "arena": {
        "nome": "Leite Longa Vida Italac Semidesnatado Zero Lactose 1l",
        "preco": 5.99,
        "preco_por_kg": 5.99
      },
      "savegnago": {
        "nome": "LEITE ZERO",
        "preco": 0,
        "preco_por_kg": 0
      },
      "mais_barato": "Tenda"
    },
    {
      "id": "43",
      "goodbom": {
        "nome": "PRESUNTO COZIDO SEARA SEM CAPA KG",
        "preco": 28.9,
        "preco_por_kg": 28.9
      },
      "tenda": {
        "nome": "Presunto Cozido Fatiado Seara 180g",
        "preco": 8.09,
        "preco_por_kg": 44.94
      },
      "arena": {
        "nome": "Presunto Cozido Nobre Sem Capa Bandeja Kg",
        "preco": 25.9,
        "preco_por_kg": 25.9
      },
      "savegnago": {
        "nome": "Presunto cozido Aurora fatiado 180g",
        "preco": 8.75,
        "preco_por_kg": 48.61
      },
      "mais_barato": "Arena"
    },
    {
      "id": "44",
      "goodbom": {
        "nome": "MORTADELA AURORA 400G",
        "preco": 5.98,
        "preco_por_kg": 14.95
      },
      "tenda": {
        "nome": "Mortadela Defumada Sadia Fatiada 180g",
        "preco": 5.45,
        "preco_por_kg": 30.28
      },
      "arena": {
        "nome": "Mortadela Aurora 1kg",
        "preco": 12.49,
        "preco_por_kg": 12.49
      },
      "savegnago": {
        "nome": "Mortadela Defumada Seara Gourmet Fatiada 180g",
        "preco": 6.59,
        "preco_por_kg": 36.61
      },
      "mais_barato": "Arena"
    },
    {
      "id": "45",
      "goodbom": {
        "nome": "BATATA CONGELADA SWIFT 400G",
        "preco": 10.5,
        "preco_por_kg": 26.25
      },
      "tenda": {
        "nome": "Batata Congelada Select 2kg",
        "preco": 21.9,
        "preco_por_kg": 10.95
      },
      "arena": {
        "nome": "Batata Congeladal Uai 2kg",
        "preco": 21.89,
        "preco_por_kg": 10.95
      },
      "savegnago": {
        "nome": "Batata Congelada Bem Brasil Palito Mais Batata 2kg",
        "preco": 28.9,
        "preco_por_kg": 14.45
      },
      "mais_barato": "Tenda"
    },
    {
      "id": "47",
      "goodbom": {
        "nome": "MANDIOCA KG",
        "preco": 4.99,
        "preco_por_kg": 4.99
      },
      "tenda": {
        "nome": "Mandioca 500g",
        "preco": 1.5,
        "preco_por_kg": 3
      },
      "arena": {
        "nome": "Mandioca Kg",
        "preco": 3.4,
        "preco_por_kg": 3.4
      },
      "savegnago": {
        "nome": "Mandioca Sertaneja Pacote 700g",
        "preco": 7.95,
        "preco_por_kg": 11.36
      },
      "mais_barato": "Tenda"
    },
    {
      "id": "50",
      "goodbom": {
        "nome": "LEITE FERMENTADO FRUTAP 850G",
        "preco": 9.99,
        "preco_por_kg": 11.75
      },
      "tenda": {
        "nome": "Leite Fermentado Nestlé Chamyto® 720G com 6 unidades",
        "preco": 10.59,
        "preco_por_kg": 14.71
      },
      "arena": {
        "nome": "Iogurte Semi Desnatado Danone Morango - 1,250kg",
        "preco": 5.99,
        "preco_por_kg": 0.02
      },
      "savegnago": {
        "nome": "Leite Fermentado Nestlé Chamyto® 450G com 6 unidades",
        "preco": 6.99,
        "preco_por_kg": 15.53
      },
      "mais_barato": "Arena"
    },
    {
      "id": "52",
      "goodbom": {
        "nome": "ARROZ INTEGRAL BROTO LEGAL 1KG",
        "preco": 5.59,
        "preco_por_kg": 5.59
      },
      "tenda": {
        "nome": "Arroz Tipo 1 Select 1Kg",
        "preco": 4,
        "preco_por_kg": 4
      },
      "arena": {
        "nome": "Arroz Solito Agulhinha 5kg",
        "preco": 19.29,
        "preco_por_kg": 3.86
      },
      "savegnago": {
        "nome": "Arroz Branco Tipo 1 - 5kg Camil",
        "preco": 23.9,
        "preco_por_kg": 4.78
      },
      "mais_barato": "Arena"
    },
    {
      "id": "56",
      "goodbom": {
        "nome": "MACARRÃO DE ARROZ PARAFUSO",
        "preco": 0,
        "preco_por_kg": 0
      },
      "tenda": {
        "nome": "Macarrão de Arroz Parafuso Urbano 500g",
        "preco": 3.75,
        "preco_por_kg": 7.5
      },
      "arena": {
        "nome": null,
        "preco": 0,
        "preco_por_kg": 0
      },
      "savegnago": {
        "nome": "MACARRÃO DE ARROZ PARAFUSO",
        "preco": 0,
        "preco_por_kg": 0
      },
      "mais_barato": "Tenda"
    },
    {
      "id": "63",
      "goodbom": {
        "nome": "TEMPERO AJINOMOTO",
        "preco": 0,
        "preco_por_kg": 0
      },
      "tenda": {
        "nome": "Tempero Ajinomoto Pet 100g",
        "preco": 8.69,
        "preco_por_kg": 86.9
      },
      "arena": {
        "nome": "Tempero Em Pó Ajino-Moto Saco 500g",
        "preco": 32.9,
        "preco_por_kg": 65.8
      },
      "savegnago": {
        "nome": "TEMPERO AJINOMOTO",
        "preco": 0,
        "preco_por_kg": 0
      },
      "mais_barato": "Arena"
    },
    {
      "id": "66",
      "goodbom": {
        "nome": "ÓLEO DE SOJA VITALIV PET 900ML",
        "preco": 7.79,
        "preco_por_kg": 8.66
      },
      "tenda": {
        "nome": "Óleo de Soja Soya Pet 900ml",
        "preco": 7.59,
        "preco_por_kg": 8.43
      },
      "arena": {
        "nome": "Óleo De Soja Vila Velha Refinado Bag 18l",
        "preco": 139,
        "preco_por_kg": 7.72
      },
      "savegnago": {
        "nome": "Óleo de Soja Soya Pet 900ml",
        "preco": 6.95,
        "preco_por_kg": 7.72
      },
      "mais_barato": "Arena"
    },
    {
      "id": "67",
      "goodbom": {
        "nome": "VINAGRE KENKO ARROZ 750ML",
        "preco": 8.49,
        "preco_por_kg": 11.32
      },
      "tenda": {
        "nome": "Vinagre de Álcool Vitalia 750ml",
        "preco": 2.69,
        "preco_por_kg": 3.59
      },
      "arena": {
        "nome": "Vinagre Palladio Álcool Colorido Pet 750ml",
        "preco": 1.79,
        "preco_por_kg": 2.39
      },
      "savegnago": {
        "nome": "Vinagre Galo de Barcelos 750ml Álcool",
        "preco": 2.75,
        "preco_por_kg": 3.67
      },
      "mais_barato": "Arena"
    },
    {
      "id": "68",
      "goodbom": {
        "nome": "MILHO VERDE BANDEJA 700G",
        "preco": 6.99,
        "preco_por_kg": 9.99
      },
      "tenda": {
        "nome": "Milho Verde Predilecta 170g",
        "preco": 2.95,
        "preco_por_kg": 17.35
      },
      "arena": {
        "nome": "Milho Verde Predilecta Lata 1,7kg",
        "preco": 27.49,
        "preco_por_kg": 3.93
      },
      "savegnago": {
        "nome": "Milho Verde Irmãos Pimenta Bandeja 600g",
        "preco": 4.95,
        "preco_por_kg": 8.25
      },
      "mais_barato": "Arena"
    },
    {
      "id": "69",
      "goodbom": {
        "nome": "SELETA DE LEGUMES LATA QUERO 170G",
        "preco": 5.99,
        "preco_por_kg": 35.24
      },
      "tenda": {
        "nome": "Seleta de Legumes Congelados De Marchi 1,02kg",
        "preco": 13.99,
        "preco_por_kg": 13.72
      },
      "arena": {
        "nome": "Seleta De Legumes Predilecta Lata 170g",
        "preco": 4.59,
        "preco_por_kg": 27
      },
      "savegnago": {
        "nome": "Seleta De Legumes 300g Agroverts",
        "preco": 5.15,
        "preco_por_kg": 17.17
      },
      "mais_barato": "Tenda"
    },
    {
      "id": "70",
      "goodbom": {
        "nome": "SARDINHA EM ÓLEO",
        "preco": 0,
        "preco_por_kg": 0
      },
      "tenda": {
        "nome": "Sardinha em Óleo Gomes da Costa 125g",
        "preco": 5.19,
        "preco_por_kg": 41.52
      },
      "arena": {
        "nome": "Sardinha 88 Ralada Em Óleo Comestível 80g",
        "preco": 4.79,
        "preco_por_kg": 59.88
      },
      "savegnago": {
        "nome": "SARDINHA EM ÓLEO",
        "preco": 0,
        "preco_por_kg": 0
      },
      "mais_barato": "Tenda"
    },
    {
      "id": "72",
      "goodbom": {
        "nome": "AÇÚCAR MASCAVO",
        "preco": 0,
        "preco_por_kg": 0
      },
      "tenda": {
        "nome": "Açúcar Mascavo Jp Pereira 1 Kg",
        "preco": 14.9,
        "preco_por_kg": 14.9
      },
      "arena": {
        "nome": "Paçoca Dacolônia Açucar Mascavo Pote 1,008kg",
        "preco": 32.99,
        "preco_por_kg": 4.12
      },
      "savegnago": {
        "nome": "Açúcar Mascavo Rosa Lima 500g",
        "preco": 6.49,
        "preco_por_kg": 12.98
      },
      "mais_barato": "Arena"
    },
    {
      "id": "75",
      "goodbom": {
        "nome": "CATCHUP",
        "preco": 0,
        "preco_por_kg": 0
      },
      "tenda": {
        "nome": "Catchup Tradicional Quero 400g",
        "preco": 7.39,
        "preco_por_kg": 18.47
      },
      "arena": {
        "nome": "Ketchup Tradicional Cepêra Squeeze 210g",
        "preco": 5.39,
        "preco_por_kg": 25.67
      },
      "savegnago": {
        "nome": "CATCHUP",
        "preco": 0,
        "preco_por_kg": 0
      },
      "mais_barato": "Tenda"
    },
    {
      "id": "76",
      "goodbom": {
        "nome": "MAIONESE VEGETAL NOT MAYO ORIGINAL SACHE 200G",
        "preco": 7.49,
        "preco_por_kg": 37.45
      },
      "tenda": {
        "nome": "Maionese Hellmann's Tradicional 335g",
        "preco": 10.39,
        "preco_por_kg": 31.01
      },
      "arena": {
        "nome": "Maionese Salada Pet 500g",
        "preco": 5.59,
        "preco_por_kg": 11.18
      },
      "savegnago": {
        "nome": "Maionese Hellmann's Tradicional 600gr",
        "preco": 10.36,
        "preco_por_kg": 17.27
      },
      "mais_barato": "Arena"
    },
    {
      "id": "77",
      "goodbom": {
        "nome": "MOSTARDA CEPERA 1010G",
        "preco": 13.99,
        "preco_por_kg": 13.85
      },
      "tenda": {
        "nome": "Mostarda Tradicional Quero 190g",
        "preco": 5.79,
        "preco_por_kg": 30.47
      },
      "arena": {
        "nome": "Mostarda Ekma Galão 3,3kg",
        "preco": 24.39,
        "preco_por_kg": 8.13
      },
      "savegnago": {
        "nome": "Mostarda Predilecta 180g Bisnaga",
        "preco": 5.65,
        "preco_por_kg": 31.39
      },
      "mais_barato": "Arena"
    },
    {
      "id": "78",
      "goodbom": {
        "nome": "LEITE CONDENSADO SEMIDESNATADO ITALAC 395G TP",
        "preco": 6.98,
        "preco_por_kg": 17.67
      },
      "tenda": {
        "nome": "Leite Condensado Semidesnatado Campos do Jordão 395g",
        "preco": 4.59,
        "preco_por_kg": 11.62
      },
      "arena": {
        "nome": "Mistura Láctea Condensada Mococa Tp 395g",
        "preco": 4.35,
        "preco_por_kg": 11.01
      },
      "savegnago": {
        "nome": "Leite Condensado TP Semidesnatado Italac 395g",
        "preco": 6.99,
        "preco_por_kg": 17.7
      },
      "mais_barato": "Arena"
    },
    {
      "id": "79",
      "goodbom": {
        "nome": "CREME DE LEITE ITALAC 200G TP",
        "preco": 3.99,
        "preco_por_kg": 19.95
      },
      "tenda": {
        "nome": "Creme de Leite Italac 200g",
        "preco": 3.25,
        "preco_por_kg": 16.25
      },
      "arena": {
        "nome": "Mistura Creme De Leite Mococa Tp 200g",
        "preco": 2.39,
        "preco_por_kg": 11.95
      },
      "savegnago": {
        "nome": "Creme de Leite 300g Nestlé",
        "preco": 9.49,
        "preco_por_kg": 31.63
      },
      "mais_barato": "Arena"
    },
    {
      "id": "80",
      "goodbom": {
        "nome": "CAPSULA DE CAFÉ",
        "preco": 0,
        "preco_por_kg": 0
      },
      "tenda": {
        "nome": "Capsula de Café Cerrado Mineiro Compativel com Nespresso 3 Corações 10 unid",
        "preco": 22.65,
        "preco_por_kg": 22.65
      },
      "arena": {
        "nome": "Café Em Cápsula Nescafé Dolce Gusto Cerrado Mineiro 10 Cápsulas",
        "preco": 23.49,
        "preco_por_kg": 23.49
      },
      "savegnago": {
        "nome": "CAPSULA DE CAFÉ",
        "preco": 0,
        "preco_por_kg": 0
      },
      "mais_barato": "Tenda"
    },
    {
      "id": "81",
      "goodbom": {
        "nome": "CAFÉ TRADICIONAL CANECÃO 500G",
        "preco": 33.99,
        "preco_por_kg": 67.98
      },
      "tenda": {
        "nome": "Café Tradicional Melitta 500g",
        "preco": 33.9,
        "preco_por_kg": 67.8
      },
      "arena": {
        "nome": "Café Bom Jesus Tradicional Vacuo 500g",
        "preco": 26.9,
        "preco_por_kg": 53.8
      },
      "savegnago": {
        "nome": "CAFÉ TRADICIONAL",
        "preco": 0,
        "preco_por_kg": 0
      },
      "mais_barato": "Arena"
    },
    {
      "id": "82",
      "goodbom": {
        "nome": "CHÁ LEÃO DE CAMOMILA 10 SACHES",
        "preco": 3.99,
        "preco_por_kg": 3.99
      },
      "tenda": {
        "nome": "Chá de Capim Cidreira Leão 15g",
        "preco": 6.29,
        "preco_por_kg": 419.33
      },
      "arena": {
        "nome": "Chá Leão Pêssego Para Preparo De Drink Sachê C/ 10 Unid. 20g",
        "preco": 14.69,
        "preco_por_kg": 734.5
      },
      "savegnago": {
        "nome": "CHÁ",
        "preco": 0,
        "preco_por_kg": 0
      },
      "mais_barato": "Goodbom"
    },
    {
      "id": "89",
      "goodbom": {
        "nome": "ÁLCOOL",
        "preco": 0,
        "preco_por_kg": 0
      },
      "tenda": {
        "nome": "Álcool Etílico Hidratado Tradicional Flops 1L",
        "preco": 5.4,
        "preco_por_kg": 5.4
      },
      "arena": {
        "nome": "Álcool Duratto Bactericida Desinfetante Neutro 1l",
        "preco": 6.79,
        "preco_por_kg": 6.79
      },
      "savegnago": {
        "nome": "ÁLCOOL",
        "preco": 0,
        "preco_por_kg": 0
      },
      "mais_barato": "Tenda"
    },
    {
      "id": "90",
      "goodbom": {
        "nome": "LIMPADOR PERFUMADO YPÊ CHÁ BRANCO 1L",
        "preco": 7.99,
        "preco_por_kg": 7.99
      },
      "tenda": {
        "nome": "Limpador Perfumado Concentrado Bambu Coala 120ml",
        "preco": 11.55,
        "preco_por_kg": 96.25
      },
      "arena": {
        "nome": "Limpador Perfumado Ypê Tropical 1l",
        "preco": 7.99,
        "preco_por_kg": 7.99
      },
      "savegnago": {
        "nome": "Limpador Perfumado Veja Lírio Do Nilo 2L",
        "preco": 9.56,
        "preco_por_kg": 4.78
      },
      "mais_barato": "Savegnago"
    },
    {
      "id": "93",
      "goodbom": {
        "nome": "LÂMPADA LED OUROLUX FRIA 20W BIVOLT",
        "preco": 10.99,
        "preco_por_kg": 10.99
      },
      "tenda": {
        "nome": "Lâmpada Led 9,0W 6.5K Bivolt Kian",
        "preco": 4.2,
        "preco_por_kg": 4.2
      },
      "arena": {
        "nome": "Lampada Ourolux Led 9w Biv 6500k Unid.",
        "preco": 5.59,
        "preco_por_kg": 5.59
      },
      "savegnago": {
        "nome": "Lâmpada Led Taschibra TKL80 12W 6500K",
        "preco": 8.99,
        "preco_por_kg": 8.99
      },
      "mais_barato": "Tenda"
    },
    {
      "id": "96",
      "goodbom": {
        "nome": "ÁGUA SANITÁRIA BARBAREX 2L",
        "preco": 5.99,
        "preco_por_kg": 3
      },
      "tenda": {
        "nome": "Água Sanitária Select 1L",
        "preco": 3.25,
        "preco_por_kg": 3.25
      },
      "arena": {
        "nome": "Água Sanitária Candura 2l",
        "preco": 5.15,
        "preco_por_kg": 2.58
      },
      "savegnago": {
        "nome": "Água Sanitária Fazenda Esperança 2L",
        "preco": 4.55,
        "preco_por_kg": 2.27
      },
      "mais_barato": "Savegnago"
    },
    {
      "id": "100",
      "goodbom": {
        "nome": "DETERGENTE CONCENTRADO YPÊ CLEAR+ 406G",
        "preco": 7.29,
        "preco_por_kg": 17.96
      },
      "tenda": {
        "nome": "Detergente Líquido Minuano Marine 500ml",
        "preco": 2.2,
        "preco_por_kg": 4.4
      },
      "arena": {
        "nome": "Detergente Ypê Capim Limão 500ml",
        "preco": 2.49,
        "preco_por_kg": 4.98
      },
      "savegnago": {
        "nome": "Detergente Ypê Clear 500ml",
        "preco": 2.59,
        "preco_por_kg": 5.18
      },
      "mais_barato": "Tenda"
    },
    {
      "id": "103",
      "goodbom": {
        "nome": "DESINFETANTE BARBAREX VIOLEX 2L",
        "preco": 5.49,
        "preco_por_kg": 2.75
      },
      "tenda": {
        "nome": "Desinfetante Jasmim Select 2L",
        "preco": 5.1,
        "preco_por_kg": 2.55
      },
      "arena": {
        "nome": "Desinfetante Barbarex Sensações 5l",
        "preco": 11.59,
        "preco_por_kg": 2.32
      },
      "savegnago": {
        "nome": "Desinfetante Líquido Lysoform Citrus 2L",
        "preco": 23.04,
        "preco_por_kg": 11.52
      },
      "mais_barato": "Arena"
    },
    {
      "id": "107",
      "goodbom": {
        "nome": "PAPEL HIGIÊNICO FOLHA DUPLA DUETTO NEUTRO C/4",
        "preco": 7.99,
        "preco_por_kg": 7.99
      },
      "tenda": {
        "nome": "Papel Higiênico Folha Simples Select 30m 4un",
        "preco": 4.3,
        "preco_por_kg": 4.3
      },
      "arena": {
        "nome": "Papel Higiênico Folha Dupla Neutro Cotton 30m",
        "preco": 19.99,
        "preco_por_kg": 19.99
      },
      "savegnago": {
        "nome": "Papel Higiênico Personal Vip Folha Dupla com 12 rolos de 30 metros",
        "preco": 21.4,
        "preco_por_kg": 21.4
      },
      "mais_barato": "Tenda"
    },
    {
      "id": "114",
      "goodbom": {
        "nome": "GEL FIXADOR TRIBAL AZUL 500G",
        "preco": 12.99,
        "preco_por_kg": 25.98
      },
      "tenda": {
        "nome": "Gel Fixador Incolor Soft Fix 250g",
        "preco": 4.9,
        "preco_por_kg": 19.6
      },
      "arena": {
        "nome": "Gel Fixador Megafix Azul Mega 260g",
        "preco": 7.59,
        "preco_por_kg": 29.19
      },
      "savegnago": {
        "nome": "Gel Fixador Clear 300g Controle Caspa",
        "preco": 17.92,
        "preco_por_kg": 59.73
      },
      "mais_barato": "Tenda"
    },
    {
      "id": "115",
      "goodbom": {
        "nome": "HASTE FLEXÍVEL",
        "preco": 0,
        "preco_por_kg": 0
      },
      "tenda": {
        "nome": "Haste Flexível Johnsons 150un",
        "preco": 13.2,
        "preco_por_kg": 13.2
      },
      "arena": {
        "nome": "Hastes Flexíveis Topz C/ 75 Unid.",
        "preco": 3.59,
        "preco_por_kg": 3.59
      },
      "savegnago": {
        "nome": "Haste Flexível Cotonetes Com 75 Unidades",
        "preco": 9.29,
        "preco_por_kg": 9.29
      },
      "mais_barato": "Arena"
    },
    {
      "id": "117",
      "goodbom": {
        "nome": "ALGODÃO SUSSEX BOLINHA COLORIDO 50G",
        "preco": 6.29,
        "preco_por_kg": 125.8
      },
      "tenda": {
        "nome": "Algodão Hidrófilo Rolo Select 50g",
        "preco": 6,
        "preco_por_kg": 120
      },
      "arena": {
        "nome": "Algodão Disco Topz Leve 100 Pague 85 C/100",
        "preco": 17.99,
        "preco_por_kg": 17.99
      },
      "savegnago": {
        "nome": "Algodão em Disco Duo Face York 50 unidades",
        "preco": 16.55,
        "preco_por_kg": 16.55
      },
      "mais_barato": "Savegnago"
    },
    {
      "id": "119",
      "goodbom": {
        "nome": "BISNAGUINHA PANCO 300G",
        "preco": 7.99,
        "preco_por_kg": 26.63
      },
      "tenda": {
        "nome": "Bisnaguinha Select 300g",
        "preco": 5.5,
        "preco_por_kg": 18.33
      },
      "arena": {
        "nome": "Pão Bisnaguinha Kim 300g",
        "preco": 7.89,
        "preco_por_kg": 26.3
      },
      "savegnago": {
        "nome": "Bisnaguinha Pullman 300g",
        "preco": 6.99,
        "preco_por_kg": 23.3
      },
      "mais_barato": "Tenda"
    }
  ]
}