{
  "ultimaAtualizacao": "23/02/2026, 13:04:33",
  "cidade": "Campinas",
  "totalCarrefour": "2187.86",
  "totalGiga": "0.00",
  "totalCovabra": "0.00",
  "totalPagueMenos": "0.00",
  "totalAtacadao": "0.00",
  "totalTenda": "0.00",
  "totalEnxuto": "0.00",
  "encontradosCarrefour": 103,
  "encontradosGiga": 0,
  "encontradosCovabra": 0,
  "encontradosPagueMenos": 0,
  "encontradosAtacadao": 0,
  "encontradosTenda": 0,
  "encontradosEnxuto": 0,
  "produtos": [
    {
      "id": "1",
      "carrefour": {
        "nome": "Ovos Jumbo Branco Katayama com 10 unidades",
        "preco": 10.99,
        "preco_por_kg": 10.99
      },
      "giga": {
        "nome": "N/A",
        "preco": 0,
        "preco_por_kg": 0
      },
      "covabra": {
        "nome": "N/A",
        "preco": 0,
        "preco_por_kg": 0
      },
      "paguemenos": {
        "nome": "N/A",
        "preco": 0,
        "preco_por_kg": 0
      },
      "atacadao": {
        "nome": "N/A",
        "preco": 0,
        "preco_por_kg": 0
      },
      "tenda": {
        "nome": "N/A",
        "preco": 0,
        "preco_por_kg": 0
      },
      "enxuto": {
        "nome": "N/A",
        "preco": 0,
        "preco_por_kg": 0
      },
      "mais_barato": "Carrefour"
    },
    {
      "id": "2",
      "carrefour": {
        "nome": "Batata Lavada Único Carrefour 1Kg",
        "preco": 3.39,
        "preco_por_kg": 3.39
      },
      "giga": {
        "nome": "N/A",
        "preco": 0,
        "preco_por_kg": 0
      },
      "covabra": {
        "nome": "N/A",
        "preco": 0,
        "preco_por_kg": 0
      },
      "paguemenos": {
        "nome": "N/A",
        "preco": 0,
        "preco_por_kg": 0
      },
      "atacadao": {
        "nome": "N/A",
        "preco": 0,
        "preco_por_kg": 0
      },
      "tenda": {
        "nome": "N/A",
        "preco": 0,
        "preco_por_kg": 0
      },
      "enxuto": {
        "nome": "N/A",
        "preco": 0,
        "preco_por_kg": 0
      },
      "mais_barato": "Carrefour"
    },
    {
      "id": "3",
      "carrefour": {
        "nome": "Cebola Carrefour Aprox. 200g",
        "preco": 0.95,
        "preco_por_kg": 4.75
      },
      "giga": {
        "nome": "N/A",
        "preco": 0,
        "preco_por_kg": 0
      },
      "covabra": {
        "nome": "N/A",
        "preco": 0,
        "preco_por_kg": 0
      },
      "paguemenos": {
        "nome": "N/A",
        "preco": 0,
        "preco_por_kg": 0
      },
      "atacadao": {
        "nome": "N/A",
        "preco": 0,
        "preco_por_kg": 0
      },
      "tenda": {
        "nome": "N/A",
        "preco": 0,
        "preco_por_kg": 0
      },
      "enxuto": {
        "nome": "N/A",
        "preco": 0,
        "preco_por_kg": 0
      },
      "mais_barato": "Carrefour"
    },
    {
      "id": "4",
      "carrefour": {
        "nome": "Tomate Italiano Carrefour Aprox. 200g",
        "preco": 1.75,
        "preco_por_kg": 8.75
      },
      "giga": {
        "nome": "N/A",
        "preco": 0,
        "preco_por_kg": 0
      },
      "covabra": {
        "nome": "N/A",
        "preco": 0,
        "preco_por_kg": 0
      },
      "paguemenos": {
        "nome": "N/A",
        "preco": 0,
        "preco_por_kg": 0
      },
      "atacadao": {
        "nome": "N/A",
        "preco": 0,
        "preco_por_kg": 0
      },
      "tenda": {
        "nome": "N/A",
        "preco": 0,
        "preco_por_kg": 0
      },
      "enxuto": {
        "nome": "N/A",
        "preco": 0,
        "preco_por_kg": 0
      },
      "mais_barato": "Carrefour"
    },
    {
      "id": "5",
      "carrefour": {
        "nome": "Pimentão Verde Carrefour Aprox. 250g",
        "preco": 3.22,
        "preco_por_kg": 12.88
      },
      "giga": {
        "nome": "N/A",
        "preco": 0,
        "preco_por_kg": 0
      },
      "covabra": {
        "nome": "N/A",
        "preco": 0,
        "preco_por_kg": 0
      },
      "paguemenos": {
        "nome": "N/A",
        "preco": 0,
        "preco_por_kg": 0
      },
      "atacadao": {
        "nome": "N/A",
        "preco": 0,
        "preco_por_kg": 0
      },
      "tenda": {
        "nome": "N/A",
        "preco": 0,
        "preco_por_kg": 0
      },
      "enxuto": {
        "nome": "N/A",
        "preco": 0,
        "preco_por_kg": 0
      },
      "mais_barato": "Carrefour"
    },
    {
      "id": "6",
      "carrefour": {
        "nome": "Pimentão Verde Carrefour Aprox. 250g",
        "preco": 3.22,
        "preco_por_kg": 12.88
      },
      "giga": {
        "nome": "N/A",
        "preco": 0,
        "preco_por_kg": 0
      },
      "covabra": {
        "nome": "N/A",
        "preco": 0,
        "preco_por_kg": 0
      },
      "paguemenos": {
        "nome": "N/A",
        "preco": 0,
        "preco_por_kg": 0
      },
      "atacadao": {
        "nome": "N/A",
        "preco": 0,
        "preco_por_kg": 0
      },
      "tenda": {
        "nome": "N/A",
        "preco": 0,
        "preco_por_kg": 0
      },
      "enxuto": {
        "nome": "N/A",
        "preco": 0,
        "preco_por_kg": 0
      },
      "mais_barato": "Carrefour"
    },
    {
      "id": "8",
      "carrefour": {
        "nome": "Limão Tahiti Carrefour Aprox. 170g",
        "preco": 0.81,
        "preco_por_kg": 4.76
      },
      "giga": {
        "nome": "N/A",
        "preco": 0,
        "preco_por_kg": 0
      },
      "covabra": {
        "nome": "N/A",
        "preco": 0,
        "preco_por_kg": 0
      },
      "paguemenos": {
        "nome": "N/A",
        "preco": 0,
        "preco_por_kg": 0
      },
      "atacadao": {
        "nome": "N/A",
        "preco": 0,
        "preco_por_kg": 0
      },
      "tenda": {
        "nome": "N/A",
        "preco": 0,
        "preco_por_kg": 0
      },
      "enxuto": {
        "nome": "N/A",
        "preco": 0,
        "preco_por_kg": 0
      },
      "mais_barato": "Carrefour"
    },
    {
      "id": "9",
      "carrefour": {
        "nome": "Vagem Macarrão Hortmix 340 g",
        "preco": 10.99,
        "preco_por_kg": 32.32
      },
      "giga": {
        "nome": "N/A",
        "preco": 0,
        "preco_por_kg": 0
      },
      "covabra": {
        "nome": "N/A",
        "preco": 0,
        "preco_por_kg": 0
      },
      "paguemenos": {
        "nome": "N/A",
        "preco": 0,
        "preco_por_kg": 0
      },
      "atacadao": {
        "nome": "N/A",
        "preco": 0,
        "preco_por_kg": 0
      },
      "tenda": {
        "nome": "N/A",
        "preco": 0,
        "preco_por_kg": 0
      },
      "enxuto": {
        "nome": "N/A",
        "preco": 0,
        "preco_por_kg": 0
      },
      "mais_barato": "Carrefour"
    },
    {
      "id": "11",
      "carrefour": {
        "nome": "Beterraba Único 1Kg",
        "preco": 4.79,
        "preco_por_kg": 4.79
      },
      "giga": {
        "nome": "N/A",
        "preco": 0,
        "preco_por_kg": 0
      },
      "covabra": {
        "nome": "N/A",
        "preco": 0,
        "preco_por_kg": 0
      },
      "paguemenos": {
        "nome": "N/A",
        "preco": 0,
        "preco_por_kg": 0
      },
      "atacadao": {
        "nome": "N/A",
        "preco": 0,
        "preco_por_kg": 0
      },
      "tenda": {
        "nome": "N/A",
        "preco": 0,
        "preco_por_kg": 0
      },
      "enxuto": {
        "nome": "N/A",
        "preco": 0,
        "preco_por_kg": 0
      },
      "mais_barato": "Carrefour"
    },
    {
      "id": "12",
      "carrefour": {
        "nome": "Mandioquinha Carrefour Aprox. 300g",
        "preco": 3.8,
        "preco_por_kg": 12.67
      },
      "giga": {
        "nome": "N/A",
        "preco": 0,
        "preco_por_kg": 0
      },
      "covabra": {
        "nome": "N/A",
        "preco": 0,
        "preco_por_kg": 0
      },
      "paguemenos": {
        "nome": "N/A",
        "preco": 0,
        "preco_por_kg": 0
      },
      "atacadao": {
        "nome": "N/A",
        "preco": 0,
        "preco_por_kg": 0
      },
      "tenda": {
        "nome": "N/A",
        "preco": 0,
        "preco_por_kg": 0
      },
      "enxuto": {
        "nome": "N/A",
        "preco": 0,
        "preco_por_kg": 0
      },
      "mais_barato": "Carrefour"
    },
    {
      "id": "13",
      "carrefour": {
        "nome": "Gengibre Aprox. 200g",
        "preco": 3.57,
        "preco_por_kg": 17.85
      },
      "giga": {
        "nome": "N/A",
        "preco": 0,
        "preco_por_kg": 0
      },
      "covabra": {
        "nome": "N/A",
        "preco": 0,
        "preco_por_kg": 0
      },
      "paguemenos": {
        "nome": "N/A",
        "preco": 0,
        "preco_por_kg": 0
      },
      "atacadao": {
        "nome": "N/A",
        "preco": 0,
        "preco_por_kg": 0
      },
      "tenda": {
        "nome": "N/A",
        "preco": 0,
        "preco_por_kg": 0
      },
      "enxuto": {
        "nome": "N/A",
        "preco": 0,
        "preco_por_kg": 0
      },
      "mais_barato": "Carrefour"
    },
    {
      "id": "14",
      "carrefour": {
        "nome": "Cenoura Carrefour Aprox. 250g",
        "preco": 0.99,
        "preco_por_kg": 3.96
      },
      "giga": {
        "nome": "N/A",
        "preco": 0,
        "preco_por_kg": 0
      },
      "covabra": {
        "nome": "N/A",
        "preco": 0,
        "preco_por_kg": 0
      },
      "paguemenos": {
        "nome": "N/A",
        "preco": 0,
        "preco_por_kg": 0
      },
      "atacadao": {
        "nome": "N/A",
        "preco": 0,
        "preco_por_kg": 0
      },
      "tenda": {
        "nome": "N/A",
        "preco": 0,
        "preco_por_kg": 0
      },
      "enxuto": {
        "nome": "N/A",
        "preco": 0,
        "preco_por_kg": 0
      },
      "mais_barato": "Carrefour"
    },
    {
      "id": "16",
      "carrefour": {
        "nome": "Mandioquinha Carrefour Aprox. 300g",
        "preco": 3.8,
        "preco_por_kg": 12.67
      },
      "giga": {
        "nome": "N/A",
        "preco": 0,
        "preco_por_kg": 0
      },
      "covabra": {
        "nome": "N/A",
        "preco": 0,
        "preco_por_kg": 0
      },
      "paguemenos": {
        "nome": "N/A",
        "preco": 0,
        "preco_por_kg": 0
      },
      "atacadao": {
        "nome": "N/A",
        "preco": 0,
        "preco_por_kg": 0
      },
      "tenda": {
        "nome": "N/A",
        "preco": 0,
        "preco_por_kg": 0
      },
      "enxuto": {
        "nome": "N/A",
        "preco": 0,
        "preco_por_kg": 0
      },
      "mais_barato": "Carrefour"
    },
    {
      "id": "17",
      "carrefour": {
        "nome": "Cheiro Verde Maço Carrefour",
        "preco": 3.79,
        "preco_por_kg": 3.79
      },
      "giga": {
        "nome": "N/A",
        "preco": 0,
        "preco_por_kg": 0
      },
      "covabra": {
        "nome": "N/A",
        "preco": 0,
        "preco_por_kg": 0
      },
      "paguemenos": {
        "nome": "N/A",
        "preco": 0,
        "preco_por_kg": 0
      },
      "atacadao": {
        "nome": "N/A",
        "preco": 0,
        "preco_por_kg": 0
      },
      "tenda": {
        "nome": "N/A",
        "preco": 0,
        "preco_por_kg": 0
      },
      "enxuto": {
        "nome": "N/A",
        "preco": 0,
        "preco_por_kg": 0
      },
      "mais_barato": "Carrefour"
    },
    {
      "id": "18",
      "carrefour": {
        "nome": "Alface Roxa Carrefour Mercado Em Unidade",
        "preco": 4.99,
        "preco_por_kg": 4.99
      },
      "giga": {
        "nome": "N/A",
        "preco": 0,
        "preco_por_kg": 0
      },
      "covabra": {
        "nome": "N/A",
        "preco": 0,
        "preco_por_kg": 0
      },
      "paguemenos": {
        "nome": "N/A",
        "preco": 0,
        "preco_por_kg": 0
      },
      "atacadao": {
        "nome": "N/A",
        "preco": 0,
        "preco_por_kg": 0
      },
      "tenda": {
        "nome": "N/A",
        "preco": 0,
        "preco_por_kg": 0
      },
      "enxuto": {
        "nome": "N/A",
        "preco": 0,
        "preco_por_kg": 0
      },
      "mais_barato": "Carrefour"
    },
    {
      "id": "19",
      "carrefour": {
        "nome": "Repolho Roxo Fresco Inteiro Carrefour Aproximadamente 1,5 kg",
        "preco": 10.48,
        "preco_por_kg": 6.99
      },
      "giga": {
        "nome": "N/A",
        "preco": 0,
        "preco_por_kg": 0
      },
      "covabra": {
        "nome": "N/A",
        "preco": 0,
        "preco_por_kg": 0
      },
      "paguemenos": {
        "nome": "N/A",
        "preco": 0,
        "preco_por_kg": 0
      },
      "atacadao": {
        "nome": "N/A",
        "preco": 0,
        "preco_por_kg": 0
      },
      "tenda": {
        "nome": "N/A",
        "preco": 0,
        "preco_por_kg": 0
      },
      "enxuto": {
        "nome": "N/A",
        "preco": 0,
        "preco_por_kg": 0
      },
      "mais_barato": "Carrefour"
    },
    {
      "id": "20",
      "carrefour": {
        "nome": "Alho em Areia Desidratado Bombay Herbs & Spices 50g",
        "preco": 14.19,
        "preco_por_kg": 283.8
      },
      "giga": {
        "nome": "N/A",
        "preco": 0,
        "preco_por_kg": 0
      },
      "covabra": {
        "nome": "N/A",
        "preco": 0,
        "preco_por_kg": 0
      },
      "paguemenos": {
        "nome": "N/A",
        "preco": 0,
        "preco_por_kg": 0
      },
      "atacadao": {
        "nome": "N/A",
        "preco": 0,
        "preco_por_kg": 0
      },
      "tenda": {
        "nome": "N/A",
        "preco": 0,
        "preco_por_kg": 0
      },
      "enxuto": {
        "nome": "N/A",
        "preco": 0,
        "preco_por_kg": 0
      },
      "mais_barato": "Carrefour"
    },
    {
      "id": "21",
      "carrefour": {
        "nome": "Mamão Formosa Garantia de Origem Aprox. 1,6 Kg",
        "preco": 13.9,
        "preco_por_kg": 8.69
      },
      "giga": {
        "nome": "N/A",
        "preco": 0,
        "preco_por_kg": 0
      },
      "covabra": {
        "nome": "N/A",
        "preco": 0,
        "preco_por_kg": 0
      },
      "paguemenos": {
        "nome": "N/A",
        "preco": 0,
        "preco_por_kg": 0
      },
      "atacadao": {
        "nome": "N/A",
        "preco": 0,
        "preco_por_kg": 0
      },
      "tenda": {
        "nome": "N/A",
        "preco": 0,
        "preco_por_kg": 0
      },
      "enxuto": {
        "nome": "N/A",
        "preco": 0,
        "preco_por_kg": 0
      },
      "mais_barato": "Carrefour"
    },
    {
      "id": "22",
      "carrefour": {
        "nome": "Banana Nanica Carrefour Aprox. 120g (estimado de cada banana)",
        "preco": 0.92,
        "preco_por_kg": 7.67
      },
      "giga": {
        "nome": "N/A",
        "preco": 0,
        "preco_por_kg": 0
      },
      "covabra": {
        "nome": "N/A",
        "preco": 0,
        "preco_por_kg": 0
      },
      "paguemenos": {
        "nome": "N/A",
        "preco": 0,
        "preco_por_kg": 0
      },
      "atacadao": {
        "nome": "N/A",
        "preco": 0,
        "preco_por_kg": 0
      },
      "tenda": {
        "nome": "N/A",
        "preco": 0,
        "preco_por_kg": 0
      },
      "enxuto": {
        "nome": "N/A",
        "preco": 0,
        "preco_por_kg": 0
      },
      "mais_barato": "Carrefour"
    },
    {
      "id": "23",
      "carrefour": {
        "nome": "Mini Tomate Mônica Uva Trebeschi",
        "preco": 8.99,
        "preco_por_kg": 8.99
      },
      "giga": {
        "nome": "N/A",
        "preco": 0,
        "preco_por_kg": 0
      },
      "covabra": {
        "nome": "N/A",
        "preco": 0,
        "preco_por_kg": 0
      },
      "paguemenos": {
        "nome": "N/A",
        "preco": 0,
        "preco_por_kg": 0
      },
      "atacadao": {
        "nome": "N/A",
        "preco": 0,
        "preco_por_kg": 0
      },
      "tenda": {
        "nome": "N/A",
        "preco": 0,
        "preco_por_kg": 0
      },
      "enxuto": {
        "nome": "N/A",
        "preco": 0,
        "preco_por_kg": 0
      },
      "mais_barato": "Carrefour"
    },
    {
      "id": "24",
      "carrefour": {
        "nome": "Maçã Gala Carrefour Aprox. 200g",
        "preco": 2.19,
        "preco_por_kg": 10.95
      },
      "giga": {
        "nome": "N/A",
        "preco": 0,
        "preco_por_kg": 0
      },
      "covabra": {
        "nome": "N/A",
        "preco": 0,
        "preco_por_kg": 0
      },
      "paguemenos": {
        "nome": "N/A",
        "preco": 0,
        "preco_por_kg": 0
      },
      "atacadao": {
        "nome": "N/A",
        "preco": 0,
        "preco_por_kg": 0
      },
      "tenda": {
        "nome": "N/A",
        "preco": 0,
        "preco_por_kg": 0
      },
      "enxuto": {
        "nome": "N/A",
        "preco": 0,
        "preco_por_kg": 0
      },
      "mais_barato": "Carrefour"
    },
    {
      "id": "25",
      "carrefour": {
        "nome": "Mexerica Importada do Uruguai Aprox. 300g",
        "preco": 4.07,
        "preco_por_kg": 13.57
      },
      "giga": {
        "nome": "N/A",
        "preco": 0,
        "preco_por_kg": 0
      },
      "covabra": {
        "nome": "N/A",
        "preco": 0,
        "preco_por_kg": 0
      },
      "paguemenos": {
        "nome": "N/A",
        "preco": 0,
        "preco_por_kg": 0
      },
      "atacadao": {
        "nome": "N/A",
        "preco": 0,
        "preco_por_kg": 0
      },
      "tenda": {
        "nome": "N/A",
        "preco": 0,
        "preco_por_kg": 0
      },
      "enxuto": {
        "nome": "N/A",
        "preco": 0,
        "preco_por_kg": 0
      },
      "mais_barato": "Carrefour"
    },
    {
      "id": "26",
      "carrefour": {
        "nome": "Margarina Cremosa com Sal Claybom Pote 500 g",
        "preco": 5.99,
        "preco_por_kg": 11.98
      },
      "giga": {
        "nome": "N/A",
        "preco": 0,
        "preco_por_kg": 0
      },
      "covabra": {
        "nome": "N/A",
        "preco": 0,
        "preco_por_kg": 0
      },
      "paguemenos": {
        "nome": "N/A",
        "preco": 0,
        "preco_por_kg": 0
      },
      "atacadao": {
        "nome": "N/A",
        "preco": 0,
        "preco_por_kg": 0
      },
      "tenda": {
        "nome": "N/A",
        "preco": 0,
        "preco_por_kg": 0
      },
      "enxuto": {
        "nome": "N/A",
        "preco": 0,
        "preco_por_kg": 0
      },
      "mais_barato": "Carrefour"
    },
    {
      "id": "27",
      "carrefour": {
        "nome": "Leite Zero Lactose Semidesnatado Parmalat ZYMIL 1L",
        "preco": 4.89,
        "preco_por_kg": 4.89
      },
      "giga": {
        "nome": "N/A",
        "preco": 0,
        "preco_por_kg": 0
      },
      "covabra": {
        "nome": "N/A",
        "preco": 0,
        "preco_por_kg": 0
      },
      "paguemenos": {
        "nome": "N/A",
        "preco": 0,
        "preco_por_kg": 0
      },
      "atacadao": {
        "nome": "N/A",
        "preco": 0,
        "preco_por_kg": 0
      },
      "tenda": {
        "nome": "N/A",
        "preco": 0,
        "preco_por_kg": 0
      },
      "enxuto": {
        "nome": "N/A",
        "preco": 0,
        "preco_por_kg": 0
      },
      "mais_barato": "Carrefour"
    },
    {
      "id": "28",
      "carrefour": {
        "nome": "Requeijão Light Zero Lactose Itambé Nolac Pote 400g",
        "preco": 17.99,
        "preco_por_kg": 44.97
      },
      "giga": {
        "nome": "N/A",
        "preco": 0,
        "preco_por_kg": 0
      },
      "covabra": {
        "nome": "N/A",
        "preco": 0,
        "preco_por_kg": 0
      },
      "paguemenos": {
        "nome": "N/A",
        "preco": 0,
        "preco_por_kg": 0
      },
      "atacadao": {
        "nome": "N/A",
        "preco": 0,
        "preco_por_kg": 0
      },
      "tenda": {
        "nome": "N/A",
        "preco": 0,
        "preco_por_kg": 0
      },
      "enxuto": {
        "nome": "N/A",
        "preco": 0,
        "preco_por_kg": 0
      },
      "mais_barato": "Carrefour"
    },
    {
      "id": "29",
      "carrefour": {
        "nome": "Queijo Mussarela Fatiado Mandaká com 150 g",
        "preco": 7.19,
        "preco_por_kg": 47.93
      },
      "giga": {
        "nome": "N/A",
        "preco": 0,
        "preco_por_kg": 0
      },
      "covabra": {
        "nome": "N/A",
        "preco": 0,
        "preco_por_kg": 0
      },
      "paguemenos": {
        "nome": "N/A",
        "preco": 0,
        "preco_por_kg": 0
      },
      "atacadao": {
        "nome": "N/A",
        "preco": 0,
        "preco_por_kg": 0
      },
      "tenda": {
        "nome": "N/A",
        "preco": 0,
        "preco_por_kg": 0
      },
      "enxuto": {
        "nome": "N/A",
        "preco": 0,
        "preco_por_kg": 0
      },
      "mais_barato": "Carrefour"
    },
    {
      "id": "30",
      "carrefour": {
        "nome": "Presunto Tipo Alemão Fatiado Hans",
        "preco": 21.89,
        "preco_por_kg": 21.89
      },
      "giga": {
        "nome": "N/A",
        "preco": 0,
        "preco_por_kg": 0
      },
      "covabra": {
        "nome": "N/A",
        "preco": 0,
        "preco_por_kg": 0
      },
      "paguemenos": {
        "nome": "N/A",
        "preco": 0,
        "preco_por_kg": 0
      },
      "atacadao": {
        "nome": "N/A",
        "preco": 0,
        "preco_por_kg": 0
      },
      "tenda": {
        "nome": "N/A",
        "preco": 0,
        "preco_por_kg": 0
      },
      "enxuto": {
        "nome": "N/A",
        "preco": 0,
        "preco_por_kg": 0
      },
      "mais_barato": "Carrefour"
    },
    {
      "id": "31",
      "carrefour": {
        "nome": "Mortadela Tubular Sadilar Familiar Sadia 1 kg",
        "preco": 16.29,
        "preco_por_kg": 16.29
      },
      "giga": {
        "nome": "N/A",
        "preco": 0,
        "preco_por_kg": 0
      },
      "covabra": {
        "nome": "N/A",
        "preco": 0,
        "preco_por_kg": 0
      },
      "paguemenos": {
        "nome": "N/A",
        "preco": 0,
        "preco_por_kg": 0
      },
      "atacadao": {
        "nome": "N/A",
        "preco": 0,
        "preco_por_kg": 0
      },
      "tenda": {
        "nome": "N/A",
        "preco": 0,
        "preco_por_kg": 0
      },
      "enxuto": {
        "nome": "N/A",
        "preco": 0,
        "preco_por_kg": 0
      },
      "mais_barato": "Carrefour"
    },
    {
      "id": "32",
      "carrefour": {
        "nome": "Batata Pré-Frita Palito Tradicional Congelada Bem Brasil Seleção Especial Pacote 1,5kg",
        "preco": 24.98,
        "preco_por_kg": 16.65
      },
      "giga": {
        "nome": "N/A",
        "preco": 0,
        "preco_por_kg": 0
      },
      "covabra": {
        "nome": "N/A",
        "preco": 0,
        "preco_por_kg": 0
      },
      "paguemenos": {
        "nome": "N/A",
        "preco": 0,
        "preco_por_kg": 0
      },
      "atacadao": {
        "nome": "N/A",
        "preco": 0,
        "preco_por_kg": 0
      },
      "tenda": {
        "nome": "N/A",
        "preco": 0,
        "preco_por_kg": 0
      },
      "enxuto": {
        "nome": "N/A",
        "preco": 0,
        "preco_por_kg": 0
      },
      "mais_barato": "Carrefour"
    },
    {
      "id": "34",
      "carrefour": {
        "nome": "Mix de Legumes Congelado Caribenha Daucy 300g",
        "preco": 20.99,
        "preco_por_kg": 69.97
      },
      "giga": {
        "nome": "N/A",
        "preco": 0,
        "preco_por_kg": 0
      },
      "covabra": {
        "nome": "N/A",
        "preco": 0,
        "preco_por_kg": 0
      },
      "paguemenos": {
        "nome": "N/A",
        "preco": 0,
        "preco_por_kg": 0
      },
      "atacadao": {
        "nome": "N/A",
        "preco": 0,
        "preco_por_kg": 0
      },
      "tenda": {
        "nome": "N/A",
        "preco": 0,
        "preco_por_kg": 0
      },
      "enxuto": {
        "nome": "N/A",
        "preco": 0,
        "preco_por_kg": 0
      },
      "mais_barato": "Carrefour"
    },
    {
      "id": "35",
      "carrefour": {
        "nome": "Água de Coco Carrefour 1 Litro",
        "preco": 7.19,
        "preco_por_kg": 7.19
      },
      "giga": {
        "nome": "N/A",
        "preco": 0,
        "preco_por_kg": 0
      },
      "covabra": {
        "nome": "N/A",
        "preco": 0,
        "preco_por_kg": 0
      },
      "paguemenos": {
        "nome": "N/A",
        "preco": 0,
        "preco_por_kg": 0
      },
      "atacadao": {
        "nome": "N/A",
        "preco": 0,
        "preco_por_kg": 0
      },
      "tenda": {
        "nome": "N/A",
        "preco": 0,
        "preco_por_kg": 0
      },
      "enxuto": {
        "nome": "N/A",
        "preco": 0,
        "preco_por_kg": 0
      },
      "mais_barato": "Carrefour"
    },
    {
      "id": "36",
      "carrefour": {
        "nome": "Leite Fermentado Yakult 40 light 80g 6 Unidades",
        "preco": 13.89,
        "preco_por_kg": 0.35
      },
      "giga": {
        "nome": "N/A",
        "preco": 0,
        "preco_por_kg": 0
      },
      "covabra": {
        "nome": "N/A",
        "preco": 0,
        "preco_por_kg": 0
      },
      "paguemenos": {
        "nome": "N/A",
        "preco": 0,
        "preco_por_kg": 0
      },
      "atacadao": {
        "nome": "N/A",
        "preco": 0,
        "preco_por_kg": 0
      },
      "tenda": {
        "nome": "N/A",
        "preco": 0,
        "preco_por_kg": 0
      },
      "enxuto": {
        "nome": "N/A",
        "preco": 0,
        "preco_por_kg": 0
      },
      "mais_barato": "Carrefour"
    },
    {
      "id": "37",
      "carrefour": {
        "nome": "Iogurte Integral Adoçado com Polpa da Fruta Sabor Morango Jamava 110g",
        "preco": 0.79,
        "preco_por_kg": 7.18
      },
      "giga": {
        "nome": "N/A",
        "preco": 0,
        "preco_por_kg": 0
      },
      "covabra": {
        "nome": "N/A",
        "preco": 0,
        "preco_por_kg": 0
      },
      "paguemenos": {
        "nome": "N/A",
        "preco": 0,
        "preco_por_kg": 0
      },
      "atacadao": {
        "nome": "N/A",
        "preco": 0,
        "preco_por_kg": 0
      },
      "tenda": {
        "nome": "N/A",
        "preco": 0,
        "preco_por_kg": 0
      },
      "enxuto": {
        "nome": "N/A",
        "preco": 0,
        "preco_por_kg": 0
      },
      "mais_barato": "Carrefour"
    },
    {
      "id": "38",
      "carrefour": {
        "nome": "Polpa de Acerola Congelada Carrefour 100g",
        "preco": 1.99,
        "preco_por_kg": 19.9
      },
      "giga": {
        "nome": "N/A",
        "preco": 0,
        "preco_por_kg": 0
      },
      "covabra": {
        "nome": "N/A",
        "preco": 0,
        "preco_por_kg": 0
      },
      "paguemenos": {
        "nome": "N/A",
        "preco": 0,
        "preco_por_kg": 0
      },
      "atacadao": {
        "nome": "N/A",
        "preco": 0,
        "preco_por_kg": 0
      },
      "tenda": {
        "nome": "N/A",
        "preco": 0,
        "preco_por_kg": 0
      },
      "enxuto": {
        "nome": "N/A",
        "preco": 0,
        "preco_por_kg": 0
      },
      "mais_barato": "Carrefour"
    },
    {
      "id": "39",
      "carrefour": {
        "nome": "Polpa De Abacaxi Com Hortelã 100g",
        "preco": 4.29,
        "preco_por_kg": 42.9
      },
      "giga": {
        "nome": "N/A",
        "preco": 0,
        "preco_por_kg": 0
      },
      "covabra": {
        "nome": "N/A",
        "preco": 0,
        "preco_por_kg": 0
      },
      "paguemenos": {
        "nome": "N/A",
        "preco": 0,
        "preco_por_kg": 0
      },
      "atacadao": {
        "nome": "N/A",
        "preco": 0,
        "preco_por_kg": 0
      },
      "tenda": {
        "nome": "N/A",
        "preco": 0,
        "preco_por_kg": 0
      },
      "enxuto": {
        "nome": "N/A",
        "preco": 0,
        "preco_por_kg": 0
      },
      "mais_barato": "Carrefour"
    },
    {
      "id": "40",
      "carrefour": {
        "nome": "Arroz Branco Camil Tipo 1 1kg",
        "preco": 3.19,
        "preco_por_kg": 3.19
      },
      "giga": {
        "nome": "N/A",
        "preco": 0,
        "preco_por_kg": 0
      },
      "covabra": {
        "nome": "N/A",
        "preco": 0,
        "preco_por_kg": 0
      },
      "paguemenos": {
        "nome": "N/A",
        "preco": 0,
        "preco_por_kg": 0
      },
      "atacadao": {
        "nome": "N/A",
        "preco": 0,
        "preco_por_kg": 0
      },
      "tenda": {
        "nome": "N/A",
        "preco": 0,
        "preco_por_kg": 0
      },
      "enxuto": {
        "nome": "N/A",
        "preco": 0,
        "preco_por_kg": 0
      },
      "mais_barato": "Carrefour"
    },
    {
      "id": "41",
      "carrefour": {
        "nome": "Feijão Preto Tipo 1 Kicaldo 1Kg",
        "preco": 5.09,
        "preco_por_kg": 5.09
      },
      "giga": {
        "nome": "N/A",
        "preco": 0,
        "preco_por_kg": 0
      },
      "covabra": {
        "nome": "N/A",
        "preco": 0,
        "preco_por_kg": 0
      },
      "paguemenos": {
        "nome": "N/A",
        "preco": 0,
        "preco_por_kg": 0
      },
      "atacadao": {
        "nome": "N/A",
        "preco": 0,
        "preco_por_kg": 0
      },
      "tenda": {
        "nome": "N/A",
        "preco": 0,
        "preco_por_kg": 0
      },
      "enxuto": {
        "nome": "N/A",
        "preco": 0,
        "preco_por_kg": 0
      },
      "mais_barato": "Carrefour"
    },
    {
      "id": "42",
      "carrefour": {
        "nome": "Macarrão Espaguete de Arroz Urbano 500g",
        "preco": 4.89,
        "preco_por_kg": 9.78
      },
      "giga": {
        "nome": "N/A",
        "preco": 0,
        "preco_por_kg": 0
      },
      "covabra": {
        "nome": "N/A",
        "preco": 0,
        "preco_por_kg": 0
      },
      "paguemenos": {
        "nome": "N/A",
        "preco": 0,
        "preco_por_kg": 0
      },
      "atacadao": {
        "nome": "N/A",
        "preco": 0,
        "preco_por_kg": 0
      },
      "tenda": {
        "nome": "N/A",
        "preco": 0,
        "preco_por_kg": 0
      },
      "enxuto": {
        "nome": "N/A",
        "preco": 0,
        "preco_por_kg": 0
      },
      "mais_barato": "Carrefour"
    },
    {
      "id": "43",
      "carrefour": {
        "nome": "Macarrão Penne Urbano Arroz Integral 500g",
        "preco": 6.89,
        "preco_por_kg": 13.78
      },
      "giga": {
        "nome": "N/A",
        "preco": 0,
        "preco_por_kg": 0
      },
      "covabra": {
        "nome": "N/A",
        "preco": 0,
        "preco_por_kg": 0
      },
      "paguemenos": {
        "nome": "N/A",
        "preco": 0,
        "preco_por_kg": 0
      },
      "atacadao": {
        "nome": "N/A",
        "preco": 0,
        "preco_por_kg": 0
      },
      "tenda": {
        "nome": "N/A",
        "preco": 0,
        "preco_por_kg": 0
      },
      "enxuto": {
        "nome": "N/A",
        "preco": 0,
        "preco_por_kg": 0
      },
      "mais_barato": "Carrefour"
    },
    {
      "id": "44",
      "carrefour": {
        "nome": "Macarrão Parafuso Zero Glúten Massa de Arroz e Feijão Urbano 500 g",
        "preco": 9.09,
        "preco_por_kg": 18.18
      },
      "giga": {
        "nome": "N/A",
        "preco": 0,
        "preco_por_kg": 0
      },
      "covabra": {
        "nome": "N/A",
        "preco": 0,
        "preco_por_kg": 0
      },
      "paguemenos": {
        "nome": "N/A",
        "preco": 0,
        "preco_por_kg": 0
      },
      "atacadao": {
        "nome": "N/A",
        "preco": 0,
        "preco_por_kg": 0
      },
      "tenda": {
        "nome": "N/A",
        "preco": 0,
        "preco_por_kg": 0
      },
      "enxuto": {
        "nome": "N/A",
        "preco": 0,
        "preco_por_kg": 0
      },
      "mais_barato": "Carrefour"
    },
    {
      "id": "45",
      "carrefour": {
        "nome": "Queijo Parmesão Ralado Vigor 100g",
        "preco": 11.09,
        "preco_por_kg": 110.9
      },
      "giga": {
        "nome": "N/A",
        "preco": 0,
        "preco_por_kg": 0
      },
      "covabra": {
        "nome": "N/A",
        "preco": 0,
        "preco_por_kg": 0
      },
      "paguemenos": {
        "nome": "N/A",
        "preco": 0,
        "preco_por_kg": 0
      },
      "atacadao": {
        "nome": "N/A",
        "preco": 0,
        "preco_por_kg": 0
      },
      "tenda": {
        "nome": "N/A",
        "preco": 0,
        "preco_por_kg": 0
      },
      "enxuto": {
        "nome": "N/A",
        "preco": 0,
        "preco_por_kg": 0
      },
      "mais_barato": "Carrefour"
    },
    {
      "id": "46",
      "carrefour": {
        "nome": "Tomate Pelado Italiano em Cubos Baronia 400g",
        "preco": 9.99,
        "preco_por_kg": 24.97
      },
      "giga": {
        "nome": "N/A",
        "preco": 0,
        "preco_por_kg": 0
      },
      "covabra": {
        "nome": "N/A",
        "preco": 0,
        "preco_por_kg": 0
      },
      "paguemenos": {
        "nome": "N/A",
        "preco": 0,
        "preco_por_kg": 0
      },
      "atacadao": {
        "nome": "N/A",
        "preco": 0,
        "preco_por_kg": 0
      },
      "tenda": {
        "nome": "N/A",
        "preco": 0,
        "preco_por_kg": 0
      },
      "enxuto": {
        "nome": "N/A",
        "preco": 0,
        "preco_por_kg": 0
      },
      "mais_barato": "Carrefour"
    },
    {
      "id": "47",
      "carrefour": {
        "nome": "Molho de Tomate Tradicional Tarantella Sachê 300 g",
        "preco": 1.69,
        "preco_por_kg": 5.63
      },
      "giga": {
        "nome": "N/A",
        "preco": 0,
        "preco_por_kg": 0
      },
      "covabra": {
        "nome": "N/A",
        "preco": 0,
        "preco_por_kg": 0
      },
      "paguemenos": {
        "nome": "N/A",
        "preco": 0,
        "preco_por_kg": 0
      },
      "atacadao": {
        "nome": "N/A",
        "preco": 0,
        "preco_por_kg": 0
      },
      "tenda": {
        "nome": "N/A",
        "preco": 0,
        "preco_por_kg": 0
      },
      "enxuto": {
        "nome": "N/A",
        "preco": 0,
        "preco_por_kg": 0
      },
      "mais_barato": "Carrefour"
    },
    {
      "id": "48",
      "carrefour": {
        "nome": "Azeite Terras de Camões Extra Virgem Frutado 500ml",
        "preco": 25.99,
        "preco_por_kg": 51.98
      },
      "giga": {
        "nome": "N/A",
        "preco": 0,
        "preco_por_kg": 0
      },
      "covabra": {
        "nome": "N/A",
        "preco": 0,
        "preco_por_kg": 0
      },
      "paguemenos": {
        "nome": "N/A",
        "preco": 0,
        "preco_por_kg": 0
      },
      "atacadao": {
        "nome": "N/A",
        "preco": 0,
        "preco_por_kg": 0
      },
      "tenda": {
        "nome": "N/A",
        "preco": 0,
        "preco_por_kg": 0
      },
      "enxuto": {
        "nome": "N/A",
        "preco": 0,
        "preco_por_kg": 0
      },
      "mais_barato": "Carrefour"
    },
    {
      "id": "49",
      "carrefour": {
        "nome": "Azeitonas Verdes sem Caroço Carrefour 120g",
        "preco": 5.79,
        "preco_por_kg": 48.25
      },
      "giga": {
        "nome": "N/A",
        "preco": 0,
        "preco_por_kg": 0
      },
      "covabra": {
        "nome": "N/A",
        "preco": 0,
        "preco_por_kg": 0
      },
      "paguemenos": {
        "nome": "N/A",
        "preco": 0,
        "preco_por_kg": 0
      },
      "atacadao": {
        "nome": "N/A",
        "preco": 0,
        "preco_por_kg": 0
      },
      "tenda": {
        "nome": "N/A",
        "preco": 0,
        "preco_por_kg": 0
      },
      "enxuto": {
        "nome": "N/A",
        "preco": 0,
        "preco_por_kg": 0
      },
      "mais_barato": "Carrefour"
    },
    {
      "id": "50",
      "carrefour": {
        "nome": "Molho Aji No Shoyu Sakura 150 ml",
        "preco": 5.69,
        "preco_por_kg": 37.93
      },
      "giga": {
        "nome": "N/A",
        "preco": 0,
        "preco_por_kg": 0
      },
      "covabra": {
        "nome": "N/A",
        "preco": 0,
        "preco_por_kg": 0
      },
      "paguemenos": {
        "nome": "N/A",
        "preco": 0,
        "preco_por_kg": 0
      },
      "atacadao": {
        "nome": "N/A",
        "preco": 0,
        "preco_por_kg": 0
      },
      "tenda": {
        "nome": "N/A",
        "preco": 0,
        "preco_por_kg": 0
      },
      "enxuto": {
        "nome": "N/A",
        "preco": 0,
        "preco_por_kg": 0
      },
      "mais_barato": "Carrefour"
    },
    {
      "id": "51",
      "carrefour": {
        "nome": "Realçador de Sabor Ajinomoto 100g",
        "preco": 13.19,
        "preco_por_kg": 131.9
      },
      "giga": {
        "nome": "N/A",
        "preco": 0,
        "preco_por_kg": 0
      },
      "covabra": {
        "nome": "N/A",
        "preco": 0,
        "preco_por_kg": 0
      },
      "paguemenos": {
        "nome": "N/A",
        "preco": 0,
        "preco_por_kg": 0
      },
      "atacadao": {
        "nome": "N/A",
        "preco": 0,
        "preco_por_kg": 0
      },
      "tenda": {
        "nome": "N/A",
        "preco": 0,
        "preco_por_kg": 0
      },
      "enxuto": {
        "nome": "N/A",
        "preco": 0,
        "preco_por_kg": 0
      },
      "mais_barato": "Carrefour"
    },
    {
      "id": "52",
      "carrefour": {
        "nome": "Farofa de Mandioca Temperada Kodilar 500g",
        "preco": 6.99,
        "preco_por_kg": 13.98
      },
      "giga": {
        "nome": "N/A",
        "preco": 0,
        "preco_por_kg": 0
      },
      "covabra": {
        "nome": "N/A",
        "preco": 0,
        "preco_por_kg": 0
      },
      "paguemenos": {
        "nome": "N/A",
        "preco": 0,
        "preco_por_kg": 0
      },
      "atacadao": {
        "nome": "N/A",
        "preco": 0,
        "preco_por_kg": 0
      },
      "tenda": {
        "nome": "N/A",
        "preco": 0,
        "preco_por_kg": 0
      },
      "enxuto": {
        "nome": "N/A",
        "preco": 0,
        "preco_por_kg": 0
      },
      "mais_barato": "Carrefour"
    },
    {
      "id": "53",
      "carrefour": {
        "nome": "Amido de Milho Kimimo 500 g",
        "preco": 9.99,
        "preco_por_kg": 19.98
      },
      "giga": {
        "nome": "N/A",
        "preco": 0,
        "preco_por_kg": 0
      },
      "covabra": {
        "nome": "N/A",
        "preco": 0,
        "preco_por_kg": 0
      },
      "paguemenos": {
        "nome": "N/A",
        "preco": 0,
        "preco_por_kg": 0
      },
      "atacadao": {
        "nome": "N/A",
        "preco": 0,
        "preco_por_kg": 0
      },
      "tenda": {
        "nome": "N/A",
        "preco": 0,
        "preco_por_kg": 0
      },
      "enxuto": {
        "nome": "N/A",
        "preco": 0,
        "preco_por_kg": 0
      },
      "mais_barato": "Carrefour"
    },
    {
      "id": "54",
      "carrefour": {
        "nome": "Óleo de Soja Soya 900ml",
        "preco": 6.29,
        "preco_por_kg": 6.99
      },
      "giga": {
        "nome": "N/A",
        "preco": 0,
        "preco_por_kg": 0
      },
      "covabra": {
        "nome": "N/A",
        "preco": 0,
        "preco_por_kg": 0
      },
      "paguemenos": {
        "nome": "N/A",
        "preco": 0,
        "preco_por_kg": 0
      },
      "atacadao": {
        "nome": "N/A",
        "preco": 0,
        "preco_por_kg": 0
      },
      "tenda": {
        "nome": "N/A",
        "preco": 0,
        "preco_por_kg": 0
      },
      "enxuto": {
        "nome": "N/A",
        "preco": 0,
        "preco_por_kg": 0
      },
      "mais_barato": "Carrefour"
    },
    {
      "id": "55",
      "carrefour": {
        "nome": "Vinagre de Álcool Colorido Toscano 750 ml",
        "preco": 3.19,
        "preco_por_kg": 4.25
      },
      "giga": {
        "nome": "N/A",
        "preco": 0,
        "preco_por_kg": 0
      },
      "covabra": {
        "nome": "N/A",
        "preco": 0,
        "preco_por_kg": 0
      },
      "paguemenos": {
        "nome": "N/A",
        "preco": 0,
        "preco_por_kg": 0
      },
      "atacadao": {
        "nome": "N/A",
        "preco": 0,
        "preco_por_kg": 0
      },
      "tenda": {
        "nome": "N/A",
        "preco": 0,
        "preco_por_kg": 0
      },
      "enxuto": {
        "nome": "N/A",
        "preco": 0,
        "preco_por_kg": 0
      },
      "mais_barato": "Carrefour"
    },
    {
      "id": "56",
      "carrefour": {
        "nome": "Milho Verde Ferrara 800g",
        "preco": 7.99,
        "preco_por_kg": 9.99
      },
      "giga": {
        "nome": "N/A",
        "preco": 0,
        "preco_por_kg": 0
      },
      "covabra": {
        "nome": "N/A",
        "preco": 0,
        "preco_por_kg": 0
      },
      "paguemenos": {
        "nome": "N/A",
        "preco": 0,
        "preco_por_kg": 0
      },
      "atacadao": {
        "nome": "N/A",
        "preco": 0,
        "preco_por_kg": 0
      },
      "tenda": {
        "nome": "N/A",
        "preco": 0,
        "preco_por_kg": 0
      },
      "enxuto": {
        "nome": "N/A",
        "preco": 0,
        "preco_por_kg": 0
      },
      "mais_barato": "Carrefour"
    },
    {
      "id": "57",
      "carrefour": {
        "nome": "Seleta de Legumes Bonduelle 300g",
        "preco": 7.19,
        "preco_por_kg": 23.97
      },
      "giga": {
        "nome": "N/A",
        "preco": 0,
        "preco_por_kg": 0
      },
      "covabra": {
        "nome": "N/A",
        "preco": 0,
        "preco_por_kg": 0
      },
      "paguemenos": {
        "nome": "N/A",
        "preco": 0,
        "preco_por_kg": 0
      },
      "atacadao": {
        "nome": "N/A",
        "preco": 0,
        "preco_por_kg": 0
      },
      "tenda": {
        "nome": "N/A",
        "preco": 0,
        "preco_por_kg": 0
      },
      "enxuto": {
        "nome": "N/A",
        "preco": 0,
        "preco_por_kg": 0
      },
      "mais_barato": "Carrefour"
    },
    {
      "id": "58",
      "carrefour": {
        "nome": "Sardinha em Óleo 88 125g",
        "preco": 5.89,
        "preco_por_kg": 47.12
      },
      "giga": {
        "nome": "N/A",
        "preco": 0,
        "preco_por_kg": 0
      },
      "covabra": {
        "nome": "N/A",
        "preco": 0,
        "preco_por_kg": 0
      },
      "paguemenos": {
        "nome": "N/A",
        "preco": 0,
        "preco_por_kg": 0
      },
      "atacadao": {
        "nome": "N/A",
        "preco": 0,
        "preco_por_kg": 0
      },
      "tenda": {
        "nome": "N/A",
        "preco": 0,
        "preco_por_kg": 0
      },
      "enxuto": {
        "nome": "N/A",
        "preco": 0,
        "preco_por_kg": 0
      },
      "mais_barato": "Carrefour"
    },
    {
      "id": "59",
      "carrefour": {
        "nome": "Açúcar Demerara Carrefour 1 Kg",
        "preco": 6.29,
        "preco_por_kg": 6.29
      },
      "giga": {
        "nome": "N/A",
        "preco": 0,
        "preco_por_kg": 0
      },
      "covabra": {
        "nome": "N/A",
        "preco": 0,
        "preco_por_kg": 0
      },
      "paguemenos": {
        "nome": "N/A",
        "preco": 0,
        "preco_por_kg": 0
      },
      "atacadao": {
        "nome": "N/A",
        "preco": 0,
        "preco_por_kg": 0
      },
      "tenda": {
        "nome": "N/A",
        "preco": 0,
        "preco_por_kg": 0
      },
      "enxuto": {
        "nome": "N/A",
        "preco": 0,
        "preco_por_kg": 0
      },
      "mais_barato": "Carrefour"
    },
    {
      "id": "60",
      "carrefour": {
        "nome": "Açúcar Mascavo Dacolonia 1kg",
        "preco": 15.99,
        "preco_por_kg": 15.99
      },
      "giga": {
        "nome": "N/A",
        "preco": 0,
        "preco_por_kg": 0
      },
      "covabra": {
        "nome": "N/A",
        "preco": 0,
        "preco_por_kg": 0
      },
      "paguemenos": {
        "nome": "N/A",
        "preco": 0,
        "preco_por_kg": 0
      },
      "atacadao": {
        "nome": "N/A",
        "preco": 0,
        "preco_por_kg": 0
      },
      "tenda": {
        "nome": "N/A",
        "preco": 0,
        "preco_por_kg": 0
      },
      "enxuto": {
        "nome": "N/A",
        "preco": 0,
        "preco_por_kg": 0
      },
      "mais_barato": "Carrefour"
    },
    {
      "id": "61",
      "carrefour": {
        "nome": "Sal Refinado Carrefour 1Kg",
        "preco": 2.19,
        "preco_por_kg": 2.19
      },
      "giga": {
        "nome": "N/A",
        "preco": 0,
        "preco_por_kg": 0
      },
      "covabra": {
        "nome": "N/A",
        "preco": 0,
        "preco_por_kg": 0
      },
      "paguemenos": {
        "nome": "N/A",
        "preco": 0,
        "preco_por_kg": 0
      },
      "atacadao": {
        "nome": "N/A",
        "preco": 0,
        "preco_por_kg": 0
      },
      "tenda": {
        "nome": "N/A",
        "preco": 0,
        "preco_por_kg": 0
      },
      "enxuto": {
        "nome": "N/A",
        "preco": 0,
        "preco_por_kg": 0
      },
      "mais_barato": "Carrefour"
    },
    {
      "id": "62",
      "carrefour": {
        "nome": "Suco de Uva Concentrado Da Fruta 500 ml",
        "preco": 4.99,
        "preco_por_kg": 9.98
      },
      "giga": {
        "nome": "N/A",
        "preco": 0,
        "preco_por_kg": 0
      },
      "covabra": {
        "nome": "N/A",
        "preco": 0,
        "preco_por_kg": 0
      },
      "paguemenos": {
        "nome": "N/A",
        "preco": 0,
        "preco_por_kg": 0
      },
      "atacadao": {
        "nome": "N/A",
        "preco": 0,
        "preco_por_kg": 0
      },
      "tenda": {
        "nome": "N/A",
        "preco": 0,
        "preco_por_kg": 0
      },
      "enxuto": {
        "nome": "N/A",
        "preco": 0,
        "preco_por_kg": 0
      },
      "mais_barato": "Carrefour"
    },
    {
      "id": "63",
      "carrefour": {
        "nome": "Ketchup Tradicional Cepêra 1,01 kg",
        "preco": 11.89,
        "preco_por_kg": 11.77
      },
      "giga": {
        "nome": "N/A",
        "preco": 0,
        "preco_por_kg": 0
      },
      "covabra": {
        "nome": "N/A",
        "preco": 0,
        "preco_por_kg": 0
      },
      "paguemenos": {
        "nome": "N/A",
        "preco": 0,
        "preco_por_kg": 0
      },
      "atacadao": {
        "nome": "N/A",
        "preco": 0,
        "preco_por_kg": 0
      },
      "tenda": {
        "nome": "N/A",
        "preco": 0,
        "preco_por_kg": 0
      },
      "enxuto": {
        "nome": "N/A",
        "preco": 0,
        "preco_por_kg": 0
      },
      "mais_barato": "Carrefour"
    },
    {
      "id": "64",
      "carrefour": {
        "nome": "Maionese Liza 450g",
        "preco": 7.09,
        "preco_por_kg": 15.76
      },
      "giga": {
        "nome": "N/A",
        "preco": 0,
        "preco_por_kg": 0
      },
      "covabra": {
        "nome": "N/A",
        "preco": 0,
        "preco_por_kg": 0
      },
      "paguemenos": {
        "nome": "N/A",
        "preco": 0,
        "preco_por_kg": 0
      },
      "atacadao": {
        "nome": "N/A",
        "preco": 0,
        "preco_por_kg": 0
      },
      "tenda": {
        "nome": "N/A",
        "preco": 0,
        "preco_por_kg": 0
      },
      "enxuto": {
        "nome": "N/A",
        "preco": 0,
        "preco_por_kg": 0
      },
      "mais_barato": "Carrefour"
    },
    {
      "id": "65",
      "carrefour": {
        "nome": "Mostarda Quero Tradicional 190 g",
        "preco": 4.89,
        "preco_por_kg": 25.74
      },
      "giga": {
        "nome": "N/A",
        "preco": 0,
        "preco_por_kg": 0
      },
      "covabra": {
        "nome": "N/A",
        "preco": 0,
        "preco_por_kg": 0
      },
      "paguemenos": {
        "nome": "N/A",
        "preco": 0,
        "preco_por_kg": 0
      },
      "atacadao": {
        "nome": "N/A",
        "preco": 0,
        "preco_por_kg": 0
      },
      "tenda": {
        "nome": "N/A",
        "preco": 0,
        "preco_por_kg": 0
      },
      "enxuto": {
        "nome": "N/A",
        "preco": 0,
        "preco_por_kg": 0
      },
      "mais_barato": "Carrefour"
    },
    {
      "id": "66",
      "carrefour": {
        "nome": "Leite Condensado Semi Desnatado Campos Jordão Caixa 395g",
        "preco": 3.99,
        "preco_por_kg": 10.1
      },
      "giga": {
        "nome": "N/A",
        "preco": 0,
        "preco_por_kg": 0
      },
      "covabra": {
        "nome": "N/A",
        "preco": 0,
        "preco_por_kg": 0
      },
      "paguemenos": {
        "nome": "N/A",
        "preco": 0,
        "preco_por_kg": 0
      },
      "atacadao": {
        "nome": "N/A",
        "preco": 0,
        "preco_por_kg": 0
      },
      "tenda": {
        "nome": "N/A",
        "preco": 0,
        "preco_por_kg": 0
      },
      "enxuto": {
        "nome": "N/A",
        "preco": 0,
        "preco_por_kg": 0
      },
      "mais_barato": "Carrefour"
    },
    {
      "id": "67",
      "carrefour": {
        "nome": "Mistura de Creme de Leite Mococa 200g",
        "preco": 2.09,
        "preco_por_kg": 10.45
      },
      "giga": {
        "nome": "N/A",
        "preco": 0,
        "preco_por_kg": 0
      },
      "covabra": {
        "nome": "N/A",
        "preco": 0,
        "preco_por_kg": 0
      },
      "paguemenos": {
        "nome": "N/A",
        "preco": 0,
        "preco_por_kg": 0
      },
      "atacadao": {
        "nome": "N/A",
        "preco": 0,
        "preco_por_kg": 0
      },
      "tenda": {
        "nome": "N/A",
        "preco": 0,
        "preco_por_kg": 0
      },
      "enxuto": {
        "nome": "N/A",
        "preco": 0,
        "preco_por_kg": 0
      },
      "mais_barato": "Carrefour"
    },
    {
      "id": "68",
      "carrefour": {
        "nome": "Café em Cápsula Espresso Orgânico Carrefour Bio 10 Unidades",
        "preco": 9.99,
        "preco_por_kg": 9.99
      },
      "giga": {
        "nome": "N/A",
        "preco": 0,
        "preco_por_kg": 0
      },
      "covabra": {
        "nome": "N/A",
        "preco": 0,
        "preco_por_kg": 0
      },
      "paguemenos": {
        "nome": "N/A",
        "preco": 0,
        "preco_por_kg": 0
      },
      "atacadao": {
        "nome": "N/A",
        "preco": 0,
        "preco_por_kg": 0
      },
      "tenda": {
        "nome": "N/A",
        "preco": 0,
        "preco_por_kg": 0
      },
      "enxuto": {
        "nome": "N/A",
        "preco": 0,
        "preco_por_kg": 0
      },
      "mais_barato": "Carrefour"
    },
    {
      "id": "69",
      "carrefour": {
        "nome": "Café Tradicional Vácuo Carrefour 500 g",
        "preco": 24.69,
        "preco_por_kg": 49.38
      },
      "giga": {
        "nome": "N/A",
        "preco": 0,
        "preco_por_kg": 0
      },
      "covabra": {
        "nome": "N/A",
        "preco": 0,
        "preco_por_kg": 0
      },
      "paguemenos": {
        "nome": "N/A",
        "preco": 0,
        "preco_por_kg": 0
      },
      "atacadao": {
        "nome": "N/A",
        "preco": 0,
        "preco_por_kg": 0
      },
      "tenda": {
        "nome": "N/A",
        "preco": 0,
        "preco_por_kg": 0
      },
      "enxuto": {
        "nome": "N/A",
        "preco": 0,
        "preco_por_kg": 0
      },
      "mais_barato": "Carrefour"
    },
    {
      "id": "70",
      "carrefour": {
        "nome": "Chá Ice Tea Leão Pêssego Zero 1,5L",
        "preco": 6.19,
        "preco_por_kg": 4.13
      },
      "giga": {
        "nome": "N/A",
        "preco": 0,
        "preco_por_kg": 0
      },
      "covabra": {
        "nome": "N/A",
        "preco": 0,
        "preco_por_kg": 0
      },
      "paguemenos": {
        "nome": "N/A",
        "preco": 0,
        "preco_por_kg": 0
      },
      "atacadao": {
        "nome": "N/A",
        "preco": 0,
        "preco_por_kg": 0
      },
      "tenda": {
        "nome": "N/A",
        "preco": 0,
        "preco_por_kg": 0
      },
      "enxuto": {
        "nome": "N/A",
        "preco": 0,
        "preco_por_kg": 0
      },
      "mais_barato": "Carrefour"
    },
    {
      "id": "71",
      "carrefour": {
        "nome": "Pipoca para Micro-Ondas Manteiga de Cinema Yoki Pacote 100g",
        "preco": 3.89,
        "preco_por_kg": 38.9
      },
      "giga": {
        "nome": "N/A",
        "preco": 0,
        "preco_por_kg": 0
      },
      "covabra": {
        "nome": "N/A",
        "preco": 0,
        "preco_por_kg": 0
      },
      "paguemenos": {
        "nome": "N/A",
        "preco": 0,
        "preco_por_kg": 0
      },
      "atacadao": {
        "nome": "N/A",
        "preco": 0,
        "preco_por_kg": 0
      },
      "tenda": {
        "nome": "N/A",
        "preco": 0,
        "preco_por_kg": 0
      },
      "enxuto": {
        "nome": "N/A",
        "preco": 0,
        "preco_por_kg": 0
      },
      "mais_barato": "Carrefour"
    },
    {
      "id": "72",
      "carrefour": {
        "nome": "Macarrão Instantâneo a Base de Arroz Bifum Sabor Carne 67g",
        "preco": 5.69,
        "preco_por_kg": 84.93
      },
      "giga": {
        "nome": "N/A",
        "preco": 0,
        "preco_por_kg": 0
      },
      "covabra": {
        "nome": "N/A",
        "preco": 0,
        "preco_por_kg": 0
      },
      "paguemenos": {
        "nome": "N/A",
        "preco": 0,
        "preco_por_kg": 0
      },
      "atacadao": {
        "nome": "N/A",
        "preco": 0,
        "preco_por_kg": 0
      },
      "tenda": {
        "nome": "N/A",
        "preco": 0,
        "preco_por_kg": 0
      },
      "enxuto": {
        "nome": "N/A",
        "preco": 0,
        "preco_por_kg": 0
      },
      "mais_barato": "Carrefour"
    },
    {
      "id": "73",
      "carrefour": {
        "nome": "Flocão de Milho Urbano Com 500g",
        "preco": 2.39,
        "preco_por_kg": 4.78
      },
      "giga": {
        "nome": "N/A",
        "preco": 0,
        "preco_por_kg": 0
      },
      "covabra": {
        "nome": "N/A",
        "preco": 0,
        "preco_por_kg": 0
      },
      "paguemenos": {
        "nome": "N/A",
        "preco": 0,
        "preco_por_kg": 0
      },
      "atacadao": {
        "nome": "N/A",
        "preco": 0,
        "preco_por_kg": 0
      },
      "tenda": {
        "nome": "N/A",
        "preco": 0,
        "preco_por_kg": 0
      },
      "enxuto": {
        "nome": "N/A",
        "preco": 0,
        "preco_por_kg": 0
      },
      "mais_barato": "Carrefour"
    },
    {
      "id": "74",
      "carrefour": {
        "nome": "Pão de Forma Seven Boys 450g",
        "preco": 6.39,
        "preco_por_kg": 14.2
      },
      "giga": {
        "nome": "N/A",
        "preco": 0,
        "preco_por_kg": 0
      },
      "covabra": {
        "nome": "N/A",
        "preco": 0,
        "preco_por_kg": 0
      },
      "paguemenos": {
        "nome": "N/A",
        "preco": 0,
        "preco_por_kg": 0
      },
      "atacadao": {
        "nome": "N/A",
        "preco": 0,
        "preco_por_kg": 0
      },
      "tenda": {
        "nome": "N/A",
        "preco": 0,
        "preco_por_kg": 0
      },
      "enxuto": {
        "nome": "N/A",
        "preco": 0,
        "preco_por_kg": 0
      },
      "mais_barato": "Carrefour"
    },
    {
      "id": "75",
      "carrefour": {
        "nome": "Tapioca Garlic Foods 1kg",
        "preco": 10.19,
        "preco_por_kg": 10.19
      },
      "giga": {
        "nome": "N/A",
        "preco": 0,
        "preco_por_kg": 0
      },
      "covabra": {
        "nome": "N/A",
        "preco": 0,
        "preco_por_kg": 0
      },
      "paguemenos": {
        "nome": "N/A",
        "preco": 0,
        "preco_por_kg": 0
      },
      "atacadao": {
        "nome": "N/A",
        "preco": 0,
        "preco_por_kg": 0
      },
      "tenda": {
        "nome": "N/A",
        "preco": 0,
        "preco_por_kg": 0
      },
      "enxuto": {
        "nome": "N/A",
        "preco": 0,
        "preco_por_kg": 0
      },
      "mais_barato": "Carrefour"
    },
    {
      "id": "76",
      "carrefour": {
        "nome": "Desinfetante Líquido Lysoform Original 2L",
        "preco": 19.09,
        "preco_por_kg": 9.54
      },
      "giga": {
        "nome": "N/A",
        "preco": 0,
        "preco_por_kg": 0
      },
      "covabra": {
        "nome": "N/A",
        "preco": 0,
        "preco_por_kg": 0
      },
      "paguemenos": {
        "nome": "N/A",
        "preco": 0,
        "preco_por_kg": 0
      },
      "atacadao": {
        "nome": "N/A",
        "preco": 0,
        "preco_por_kg": 0
      },
      "tenda": {
        "nome": "N/A",
        "preco": 0,
        "preco_por_kg": 0
      },
      "enxuto": {
        "nome": "N/A",
        "preco": 0,
        "preco_por_kg": 0
      },
      "mais_barato": "Carrefour"
    },
    {
      "id": "77",
      "carrefour": {
        "nome": "Álcool Liquido Com Bicarbonato Zulu 1l",
        "preco": 6.59,
        "preco_por_kg": 6.59
      },
      "giga": {
        "nome": "N/A",
        "preco": 0,
        "preco_por_kg": 0
      },
      "covabra": {
        "nome": "N/A",
        "preco": 0,
        "preco_por_kg": 0
      },
      "paguemenos": {
        "nome": "N/A",
        "preco": 0,
        "preco_por_kg": 0
      },
      "atacadao": {
        "nome": "N/A",
        "preco": 0,
        "preco_por_kg": 0
      },
      "tenda": {
        "nome": "N/A",
        "preco": 0,
        "preco_por_kg": 0
      },
      "enxuto": {
        "nome": "N/A",
        "preco": 0,
        "preco_por_kg": 0
      },
      "mais_barato": "Carrefour"
    },
    {
      "id": "78",
      "carrefour": {
        "nome": "Limpador Multiuso Ypê Desengordurante 500ml",
        "preco": 3.69,
        "preco_por_kg": 7.38
      },
      "giga": {
        "nome": "N/A",
        "preco": 0,
        "preco_por_kg": 0
      },
      "covabra": {
        "nome": "N/A",
        "preco": 0,
        "preco_por_kg": 0
      },
      "paguemenos": {
        "nome": "N/A",
        "preco": 0,
        "preco_por_kg": 0
      },
      "atacadao": {
        "nome": "N/A",
        "preco": 0,
        "preco_por_kg": 0
      },
      "tenda": {
        "nome": "N/A",
        "preco": 0,
        "preco_por_kg": 0
      },
      "enxuto": {
        "nome": "N/A",
        "preco": 0,
        "preco_por_kg": 0
      },
      "mais_barato": "Carrefour"
    },
    {
      "id": "79",
      "carrefour": {
        "nome": "Removedor de Esmalte Carrefour 100ml",
        "preco": 4.9,
        "preco_por_kg": 49
      },
      "giga": {
        "nome": "N/A",
        "preco": 0,
        "preco_por_kg": 0
      },
      "covabra": {
        "nome": "N/A",
        "preco": 0,
        "preco_por_kg": 0
      },
      "paguemenos": {
        "nome": "N/A",
        "preco": 0,
        "preco_por_kg": 0
      },
      "atacadao": {
        "nome": "N/A",
        "preco": 0,
        "preco_por_kg": 0
      },
      "tenda": {
        "nome": "N/A",
        "preco": 0,
        "preco_por_kg": 0
      },
      "enxuto": {
        "nome": "N/A",
        "preco": 0,
        "preco_por_kg": 0
      },
      "mais_barato": "Carrefour"
    },
    {
      "id": "80",
      "carrefour": {
        "nome": "Aromatizador Bom Ar Aerossol Campos de Lavanda Embalagem Econômica 360ml",
        "preco": 17.49,
        "preco_por_kg": 48.58
      },
      "giga": {
        "nome": "N/A",
        "preco": 0,
        "preco_por_kg": 0
      },
      "covabra": {
        "nome": "N/A",
        "preco": 0,
        "preco_por_kg": 0
      },
      "paguemenos": {
        "nome": "N/A",
        "preco": 0,
        "preco_por_kg": 0
      },
      "atacadao": {
        "nome": "N/A",
        "preco": 0,
        "preco_por_kg": 0
      },
      "tenda": {
        "nome": "N/A",
        "preco": 0,
        "preco_por_kg": 0
      },
      "enxuto": {
        "nome": "N/A",
        "preco": 0,
        "preco_por_kg": 0
      },
      "mais_barato": "Carrefour"
    },
    {
      "id": "81",
      "carrefour": {
        "nome": "Lâmpada Superled Bulbo 9 W Luz Amarela Bivolt E27 Ourolux",
        "preco": 3.99,
        "preco_por_kg": 3.99
      },
      "giga": {
        "nome": "N/A",
        "preco": 0,
        "preco_por_kg": 0
      },
      "covabra": {
        "nome": "N/A",
        "preco": 0,
        "preco_por_kg": 0
      },
      "paguemenos": {
        "nome": "N/A",
        "preco": 0,
        "preco_por_kg": 0
      },
      "atacadao": {
        "nome": "N/A",
        "preco": 0,
        "preco_por_kg": 0
      },
      "tenda": {
        "nome": "N/A",
        "preco": 0,
        "preco_por_kg": 0
      },
      "enxuto": {
        "nome": "N/A",
        "preco": 0,
        "preco_por_kg": 0
      },
      "mais_barato": "Carrefour"
    },
    {
      "id": "82",
      "carrefour": {
        "nome": "Saco de Lixo Preto 100l Embalixo Pacote com 10 Unidades",
        "preco": 5.99,
        "preco_por_kg": 0.06
      },
      "giga": {
        "nome": "N/A",
        "preco": 0,
        "preco_por_kg": 0
      },
      "covabra": {
        "nome": "N/A",
        "preco": 0,
        "preco_por_kg": 0
      },
      "paguemenos": {
        "nome": "N/A",
        "preco": 0,
        "preco_por_kg": 0
      },
      "atacadao": {
        "nome": "N/A",
        "preco": 0,
        "preco_por_kg": 0
      },
      "tenda": {
        "nome": "N/A",
        "preco": 0,
        "preco_por_kg": 0
      },
      "enxuto": {
        "nome": "N/A",
        "preco": 0,
        "preco_por_kg": 0
      },
      "mais_barato": "Carrefour"
    },
    {
      "id": "83",
      "carrefour": {
        "nome": "Saco de Lixo Preto 50l Embalixo Pacote com 20 Unidades",
        "preco": 5.99,
        "preco_por_kg": 0.12
      },
      "giga": {
        "nome": "N/A",
        "preco": 0,
        "preco_por_kg": 0
      },
      "covabra": {
        "nome": "N/A",
        "preco": 0,
        "preco_por_kg": 0
      },
      "paguemenos": {
        "nome": "N/A",
        "preco": 0,
        "preco_por_kg": 0
      },
      "atacadao": {
        "nome": "N/A",
        "preco": 0,
        "preco_por_kg": 0
      },
      "tenda": {
        "nome": "N/A",
        "preco": 0,
        "preco_por_kg": 0
      },
      "enxuto": {
        "nome": "N/A",
        "preco": 0,
        "preco_por_kg": 0
      },
      "mais_barato": "Carrefour"
    },
    {
      "id": "84",
      "carrefour": {
        "nome": "Água Sanitária Olimpo 2L",
        "preco": 3.59,
        "preco_por_kg": 1.79
      },
      "giga": {
        "nome": "N/A",
        "preco": 0,
        "preco_por_kg": 0
      },
      "covabra": {
        "nome": "N/A",
        "preco": 0,
        "preco_por_kg": 0
      },
      "paguemenos": {
        "nome": "N/A",
        "preco": 0,
        "preco_por_kg": 0
      },
      "atacadao": {
        "nome": "N/A",
        "preco": 0,
        "preco_por_kg": 0
      },
      "tenda": {
        "nome": "N/A",
        "preco": 0,
        "preco_por_kg": 0
      },
      "enxuto": {
        "nome": "N/A",
        "preco": 0,
        "preco_por_kg": 0
      },
      "mais_barato": "Carrefour"
    },
    {
      "id": "85",
      "carrefour": {
        "nome": "Lava-Roupas Líquido Lavanda Omo Galão 3 L",
        "preco": 40.29,
        "preco_por_kg": 13.43
      },
      "giga": {
        "nome": "N/A",
        "preco": 0,
        "preco_por_kg": 0
      },
      "covabra": {
        "nome": "N/A",
        "preco": 0,
        "preco_por_kg": 0
      },
      "paguemenos": {
        "nome": "N/A",
        "preco": 0,
        "preco_por_kg": 0
      },
      "atacadao": {
        "nome": "N/A",
        "preco": 0,
        "preco_por_kg": 0
      },
      "tenda": {
        "nome": "N/A",
        "preco": 0,
        "preco_por_kg": 0
      },
      "enxuto": {
        "nome": "N/A",
        "preco": 0,
        "preco_por_kg": 0
      },
      "mais_barato": "Carrefour"
    },
    {
      "id": "86",
      "carrefour": {
        "nome": "Amaciante Ypê Tradicional Aconchego 5L",
        "preco": 20.59,
        "preco_por_kg": 4.12
      },
      "giga": {
        "nome": "N/A",
        "preco": 0,
        "preco_por_kg": 0
      },
      "covabra": {
        "nome": "N/A",
        "preco": 0,
        "preco_por_kg": 0
      },
      "paguemenos": {
        "nome": "N/A",
        "preco": 0,
        "preco_por_kg": 0
      },
      "atacadao": {
        "nome": "N/A",
        "preco": 0,
        "preco_por_kg": 0
      },
      "tenda": {
        "nome": "N/A",
        "preco": 0,
        "preco_por_kg": 0
      },
      "enxuto": {
        "nome": "N/A",
        "preco": 0,
        "preco_por_kg": 0
      },
      "mais_barato": "Carrefour"
    },
    {
      "id": "87",
      "carrefour": {
        "nome": "Detergente Líquido Carrefour Clear 500ml",
        "preco": 1.79,
        "preco_por_kg": 3.58
      },
      "giga": {
        "nome": "N/A",
        "preco": 0,
        "preco_por_kg": 0
      },
      "covabra": {
        "nome": "N/A",
        "preco": 0,
        "preco_por_kg": 0
      },
      "paguemenos": {
        "nome": "N/A",
        "preco": 0,
        "preco_por_kg": 0
      },
      "atacadao": {
        "nome": "N/A",
        "preco": 0,
        "preco_por_kg": 0
      },
      "tenda": {
        "nome": "N/A",
        "preco": 0,
        "preco_por_kg": 0
      },
      "enxuto": {
        "nome": "N/A",
        "preco": 0,
        "preco_por_kg": 0
      },
      "mais_barato": "Carrefour"
    },
    {
      "id": "88",
      "carrefour": {
        "nome": "Limpador Multiuso Ypê Desengordurante 500ml",
        "preco": 3.69,
        "preco_por_kg": 7.38
      },
      "giga": {
        "nome": "N/A",
        "preco": 0,
        "preco_por_kg": 0
      },
      "covabra": {
        "nome": "N/A",
        "preco": 0,
        "preco_por_kg": 0
      },
      "paguemenos": {
        "nome": "N/A",
        "preco": 0,
        "preco_por_kg": 0
      },
      "atacadao": {
        "nome": "N/A",
        "preco": 0,
        "preco_por_kg": 0
      },
      "tenda": {
        "nome": "N/A",
        "preco": 0,
        "preco_por_kg": 0
      },
      "enxuto": {
        "nome": "N/A",
        "preco": 0,
        "preco_por_kg": 0
      },
      "mais_barato": "Carrefour"
    },
    {
      "id": "89",
      "carrefour": {
        "nome": "Limpa Piso com Cloro Carrefour Limpeza Pesada Original 1 Litro",
        "preco": 7.59,
        "preco_por_kg": 7.59
      },
      "giga": {
        "nome": "N/A",
        "preco": 0,
        "preco_por_kg": 0
      },
      "covabra": {
        "nome": "N/A",
        "preco": 0,
        "preco_por_kg": 0
      },
      "paguemenos": {
        "nome": "N/A",
        "preco": 0,
        "preco_por_kg": 0
      },
      "atacadao": {
        "nome": "N/A",
        "preco": 0,
        "preco_por_kg": 0
      },
      "tenda": {
        "nome": "N/A",
        "preco": 0,
        "preco_por_kg": 0
      },
      "enxuto": {
        "nome": "N/A",
        "preco": 0,
        "preco_por_kg": 0
      },
      "mais_barato": "Carrefour"
    },
    {
      "id": "90",
      "carrefour": {
        "nome": "Desinfetante Urca Lavanda 2 Litros",
        "preco": 4.69,
        "preco_por_kg": 2.35
      },
      "giga": {
        "nome": "N/A",
        "preco": 0,
        "preco_por_kg": 0
      },
      "covabra": {
        "nome": "N/A",
        "preco": 0,
        "preco_por_kg": 0
      },
      "paguemenos": {
        "nome": "N/A",
        "preco": 0,
        "preco_por_kg": 0
      },
      "atacadao": {
        "nome": "N/A",
        "preco": 0,
        "preco_por_kg": 0
      },
      "tenda": {
        "nome": "N/A",
        "preco": 0,
        "preco_por_kg": 0
      },
      "enxuto": {
        "nome": "N/A",
        "preco": 0,
        "preco_por_kg": 0
      },
      "mais_barato": "Carrefour"
    },
    {
      "id": "91",
      "carrefour": {
        "nome": "Esponja Multiuso Bombril 1 Unidade",
        "preco": 1.89,
        "preco_por_kg": 1.89
      },
      "giga": {
        "nome": "N/A",
        "preco": 0,
        "preco_por_kg": 0
      },
      "covabra": {
        "nome": "N/A",
        "preco": 0,
        "preco_por_kg": 0
      },
      "paguemenos": {
        "nome": "N/A",
        "preco": 0,
        "preco_por_kg": 0
      },
      "atacadao": {
        "nome": "N/A",
        "preco": 0,
        "preco_por_kg": 0
      },
      "tenda": {
        "nome": "N/A",
        "preco": 0,
        "preco_por_kg": 0
      },
      "enxuto": {
        "nome": "N/A",
        "preco": 0,
        "preco_por_kg": 0
      },
      "mais_barato": "Carrefour"
    },
    {
      "id": "92",
      "carrefour": {
        "nome": "Esponja Multiuso Bombril 1 Unidade",
        "preco": 1.89,
        "preco_por_kg": 1.89
      },
      "giga": {
        "nome": "N/A",
        "preco": 0,
        "preco_por_kg": 0
      },
      "covabra": {
        "nome": "N/A",
        "preco": 0,
        "preco_por_kg": 0
      },
      "paguemenos": {
        "nome": "N/A",
        "preco": 0,
        "preco_por_kg": 0
      },
      "atacadao": {
        "nome": "N/A",
        "preco": 0,
        "preco_por_kg": 0
      },
      "tenda": {
        "nome": "N/A",
        "preco": 0,
        "preco_por_kg": 0
      },
      "enxuto": {
        "nome": "N/A",
        "preco": 0,
        "preco_por_kg": 0
      },
      "mais_barato": "Carrefour"
    },
    {
      "id": "93",
      "carrefour": {
        "nome": "Fralda Descartável Infantil Huggies Máxima Proteção XG 12 a 15kg Pacote 56 Unidades Leve Mais Pague Menos",
        "preco": 95.99,
        "preco_por_kg": 6.4
      },
      "giga": {
        "nome": "N/A",
        "preco": 0,
        "preco_por_kg": 0
      },
      "covabra": {
        "nome": "N/A",
        "preco": 0,
        "preco_por_kg": 0
      },
      "paguemenos": {
        "nome": "N/A",
        "preco": 0,
        "preco_por_kg": 0
      },
      "atacadao": {
        "nome": "N/A",
        "preco": 0,
        "preco_por_kg": 0
      },
      "tenda": {
        "nome": "N/A",
        "preco": 0,
        "preco_por_kg": 0
      },
      "enxuto": {
        "nome": "N/A",
        "preco": 0,
        "preco_por_kg": 0
      },
      "mais_barato": "Carrefour"
    },
    {
      "id": "94",
      "carrefour": {
        "nome": "Papel Higiênico Folha Simples 30m Sublime Leve 12 Pague 11",
        "preco": 10.69,
        "preco_por_kg": 10.69
      },
      "giga": {
        "nome": "N/A",
        "preco": 0,
        "preco_por_kg": 0
      },
      "covabra": {
        "nome": "N/A",
        "preco": 0,
        "preco_por_kg": 0
      },
      "paguemenos": {
        "nome": "N/A",
        "preco": 0,
        "preco_por_kg": 0
      },
      "atacadao": {
        "nome": "N/A",
        "preco": 0,
        "preco_por_kg": 0
      },
      "tenda": {
        "nome": "N/A",
        "preco": 0,
        "preco_por_kg": 0
      },
      "enxuto": {
        "nome": "N/A",
        "preco": 0,
        "preco_por_kg": 0
      },
      "mais_barato": "Carrefour"
    },
    {
      "id": "95",
      "carrefour": {
        "nome": "Desodorizador Sanitário Pato Gel Adesivo Marine Refil 6 Discos",
        "preco": 16.89,
        "preco_por_kg": 16.89
      },
      "giga": {
        "nome": "N/A",
        "preco": 0,
        "preco_por_kg": 0
      },
      "covabra": {
        "nome": "N/A",
        "preco": 0,
        "preco_por_kg": 0
      },
      "paguemenos": {
        "nome": "N/A",
        "preco": 0,
        "preco_por_kg": 0
      },
      "atacadao": {
        "nome": "N/A",
        "preco": 0,
        "preco_por_kg": 0
      },
      "tenda": {
        "nome": "N/A",
        "preco": 0,
        "preco_por_kg": 0
      },
      "enxuto": {
        "nome": "N/A",
        "preco": 0,
        "preco_por_kg": 0
      },
      "mais_barato": "Carrefour"
    },
    {
      "id": "96",
      "carrefour": {
        "nome": "Escova Dental Carrefour Soft Advantage Macia 1 unidade",
        "preco": 7.49,
        "preco_por_kg": 7.49
      },
      "giga": {
        "nome": "N/A",
        "preco": 0,
        "preco_por_kg": 0
      },
      "covabra": {
        "nome": "N/A",
        "preco": 0,
        "preco_por_kg": 0
      },
      "paguemenos": {
        "nome": "N/A",
        "preco": 0,
        "preco_por_kg": 0
      },
      "atacadao": {
        "nome": "N/A",
        "preco": 0,
        "preco_por_kg": 0
      },
      "tenda": {
        "nome": "N/A",
        "preco": 0,
        "preco_por_kg": 0
      },
      "enxuto": {
        "nome": "N/A",
        "preco": 0,
        "preco_por_kg": 0
      },
      "mais_barato": "Carrefour"
    },
    {
      "id": "97",
      "carrefour": {
        "nome": "Creme Dental Infantil Boni Kids Mundo dos Carros Menta 50g",
        "preco": 1.99,
        "preco_por_kg": 39.8
      },
      "giga": {
        "nome": "N/A",
        "preco": 0,
        "preco_por_kg": 0
      },
      "covabra": {
        "nome": "N/A",
        "preco": 0,
        "preco_por_kg": 0
      },
      "paguemenos": {
        "nome": "N/A",
        "preco": 0,
        "preco_por_kg": 0
      },
      "atacadao": {
        "nome": "N/A",
        "preco": 0,
        "preco_por_kg": 0
      },
      "tenda": {
        "nome": "N/A",
        "preco": 0,
        "preco_por_kg": 0
      },
      "enxuto": {
        "nome": "N/A",
        "preco": 0,
        "preco_por_kg": 0
      },
      "mais_barato": "Carrefour"
    },
    {
      "id": "98",
      "carrefour": {
        "nome": "Sabonete Líquido Suavidade Delicada Corporal Palmolive Naturals Sachê 200ml Refil",
        "preco": 7.09,
        "preco_por_kg": 35.45
      },
      "giga": {
        "nome": "N/A",
        "preco": 0,
        "preco_por_kg": 0
      },
      "covabra": {
        "nome": "N/A",
        "preco": 0,
        "preco_por_kg": 0
      },
      "paguemenos": {
        "nome": "N/A",
        "preco": 0,
        "preco_por_kg": 0
      },
      "atacadao": {
        "nome": "N/A",
        "preco": 0,
        "preco_por_kg": 0
      },
      "tenda": {
        "nome": "N/A",
        "preco": 0,
        "preco_por_kg": 0
      },
      "enxuto": {
        "nome": "N/A",
        "preco": 0,
        "preco_por_kg": 0
      },
      "mais_barato": "Carrefour"
    },
    {
      "id": "99",
      "carrefour": {
        "nome": "Sabonete em Barra Sensação Purificante Argila Preta e Óleo de Eucalipto Palmolive Naturals 150g Tamanho Familiar",
        "preco": 4.09,
        "preco_por_kg": 27.27
      },
      "giga": {
        "nome": "N/A",
        "preco": 0,
        "preco_por_kg": 0
      },
      "covabra": {
        "nome": "N/A",
        "preco": 0,
        "preco_por_kg": 0
      },
      "paguemenos": {
        "nome": "N/A",
        "preco": 0,
        "preco_por_kg": 0
      },
      "atacadao": {
        "nome": "N/A",
        "preco": 0,
        "preco_por_kg": 0
      },
      "tenda": {
        "nome": "N/A",
        "preco": 0,
        "preco_por_kg": 0
      },
      "enxuto": {
        "nome": "N/A",
        "preco": 0,
        "preco_por_kg": 0
      },
      "mais_barato": "Carrefour"
    },
    {
      "id": "100",
      "carrefour": {
        "nome": "Sabonete em Barra para Bebê Pom Pom Loção Hidratante 80g",
        "preco": 4.79,
        "preco_por_kg": 59.88
      },
      "giga": {
        "nome": "N/A",
        "preco": 0,
        "preco_por_kg": 0
      },
      "covabra": {
        "nome": "N/A",
        "preco": 0,
        "preco_por_kg": 0
      },
      "paguemenos": {
        "nome": "N/A",
        "preco": 0,
        "preco_por_kg": 0
      },
      "atacadao": {
        "nome": "N/A",
        "preco": 0,
        "preco_por_kg": 0
      },
      "tenda": {
        "nome": "N/A",
        "preco": 0,
        "preco_por_kg": 0
      },
      "enxuto": {
        "nome": "N/A",
        "preco": 0,
        "preco_por_kg": 0
      },
      "mais_barato": "Carrefour"
    },
    {
      "id": "101",
      "carrefour": {
        "nome": "Gel Fixador Carrefour Men Incolor 230 g",
        "preco": 5.79,
        "preco_por_kg": 25.17
      },
      "giga": {
        "nome": "N/A",
        "preco": 0,
        "preco_por_kg": 0
      },
      "covabra": {
        "nome": "N/A",
        "preco": 0,
        "preco_por_kg": 0
      },
      "paguemenos": {
        "nome": "N/A",
        "preco": 0,
        "preco_por_kg": 0
      },
      "atacadao": {
        "nome": "N/A",
        "preco": 0,
        "preco_por_kg": 0
      },
      "tenda": {
        "nome": "N/A",
        "preco": 0,
        "preco_por_kg": 0
      },
      "enxuto": {
        "nome": "N/A",
        "preco": 0,
        "preco_por_kg": 0
      },
      "mais_barato": "Carrefour"
    },
    {
      "id": "102",
      "carrefour": {
        "nome": "Hastes Flexíveis Carrefour Soft 75 unidades",
        "preco": 2.9,
        "preco_por_kg": 2.9
      },
      "giga": {
        "nome": "N/A",
        "preco": 0,
        "preco_por_kg": 0
      },
      "covabra": {
        "nome": "N/A",
        "preco": 0,
        "preco_por_kg": 0
      },
      "paguemenos": {
        "nome": "N/A",
        "preco": 0,
        "preco_por_kg": 0
      },
      "atacadao": {
        "nome": "N/A",
        "preco": 0,
        "preco_por_kg": 0
      },
      "tenda": {
        "nome": "N/A",
        "preco": 0,
        "preco_por_kg": 0
      },
      "enxuto": {
        "nome": "N/A",
        "preco": 0,
        "preco_por_kg": 0
      },
      "mais_barato": "Carrefour"
    },
    {
      "id": "103",
      "carrefour": {
        "nome": "Lenço Umedecido Carrefour Hora de Dormir 48 Lenços",
        "preco": 7.79,
        "preco_por_kg": 0.16
      },
      "giga": {
        "nome": "N/A",
        "preco": 0,
        "preco_por_kg": 0
      },
      "covabra": {
        "nome": "N/A",
        "preco": 0,
        "preco_por_kg": 0
      },
      "paguemenos": {
        "nome": "N/A",
        "preco": 0,
        "preco_por_kg": 0
      },
      "atacadao": {
        "nome": "N/A",
        "preco": 0,
        "preco_por_kg": 0
      },
      "tenda": {
        "nome": "N/A",
        "preco": 0,
        "preco_por_kg": 0
      },
      "enxuto": {
        "nome": "N/A",
        "preco": 0,
        "preco_por_kg": 0
      },
      "mais_barato": "Carrefour"
    },
    {
      "id": "104",
      "carrefour": {
        "nome": "Fronha 100% algodão Teka Crystal 050 x 070 cm",
        "preco": 8.99,
        "preco_por_kg": 8.99
      },
      "giga": {
        "nome": "N/A",
        "preco": 0,
        "preco_por_kg": 0
      },
      "covabra": {
        "nome": "N/A",
        "preco": 0,
        "preco_por_kg": 0
      },
      "paguemenos": {
        "nome": "N/A",
        "preco": 0,
        "preco_por_kg": 0
      },
      "atacadao": {
        "nome": "N/A",
        "preco": 0,
        "preco_por_kg": 0
      },
      "tenda": {
        "nome": "N/A",
        "preco": 0,
        "preco_por_kg": 0
      },
      "enxuto": {
        "nome": "N/A",
        "preco": 0,
        "preco_por_kg": 0
      },
      "mais_barato": "Carrefour"
    },
    {
      "id": "105",
      "carrefour": {
        "nome": "Enxaguante Bucal Hortelã Listerine Cool Mint 1,5l Leve Mais Pague Menos",
        "preco": 51.99,
        "preco_por_kg": 34.66
      },
      "giga": {
        "nome": "N/A",
        "preco": 0,
        "preco_por_kg": 0
      },
      "covabra": {
        "nome": "N/A",
        "preco": 0,
        "preco_por_kg": 0
      },
      "paguemenos": {
        "nome": "N/A",
        "preco": 0,
        "preco_por_kg": 0
      },
      "atacadao": {
        "nome": "N/A",
        "preco": 0,
        "preco_por_kg": 0
      },
      "tenda": {
        "nome": "N/A",
        "preco": 0,
        "preco_por_kg": 0
      },
      "enxuto": {
        "nome": "N/A",
        "preco": 0,
        "preco_por_kg": 0
      },
      "mais_barato": "Carrefour"
    },
    {
      "id": "106",
      "carrefour": {
        "nome": "Bisnaguinha Kim 300g",
        "preco": 4.99,
        "preco_por_kg": 16.63
      },
      "giga": {
        "nome": "N/A",
        "preco": 0,
        "preco_por_kg": 0
      },
      "covabra": {
        "nome": "N/A",
        "preco": 0,
        "preco_por_kg": 0
      },
      "paguemenos": {
        "nome": "N/A",
        "preco": 0,
        "preco_por_kg": 0
      },
      "atacadao": {
        "nome": "N/A",
        "preco": 0,
        "preco_por_kg": 0
      },
      "tenda": {
        "nome": "N/A",
        "preco": 0,
        "preco_por_kg": 0
      },
      "enxuto": {
        "nome": "N/A",
        "preco": 0,
        "preco_por_kg": 0
      },
      "mais_barato": "Carrefour"
    },
    {
      "id": "108",
      "carrefour": {
        "nome": "Fubá Mimoso Yoki Pacote 500g",
        "preco": 4.69,
        "preco_por_kg": 9.38
      },
      "giga": {
        "nome": "N/A",
        "preco": 0,
        "preco_por_kg": 0
      },
      "covabra": {
        "nome": "N/A",
        "preco": 0,
        "preco_por_kg": 0
      },
      "paguemenos": {
        "nome": "N/A",
        "preco": 0,
        "preco_por_kg": 0
      },
      "atacadao": {
        "nome": "N/A",
        "preco": 0,
        "preco_por_kg": 0
      },
      "tenda": {
        "nome": "N/A",
        "preco": 0,
        "preco_por_kg": 0
      },
      "enxuto": {
        "nome": "N/A",
        "preco": 0,
        "preco_por_kg": 0
      },
      "mais_barato": "Carrefour"
    }
  ]
}